[
  {
    "words": [
      "Condomines,",
      "B.",
      "B.",
      "Hennequin,",
      "\u00c9.",
      "\u00c9.",
      "&",
      "Borteyrou,",
      "X.",
      "X.",
      "2015",
      "2015",
      "D\u00e9tection",
      "des",
      "comp\u00e9tences",
      "manag\u00e9riales-Quels",
      "sont",
      "les",
      "atouts",
      "du",
      "mod\u00e8le",
      "analogique?",
      "analogique?",
      "Revue",
      "Fran\u00e7aise",
      "de",
      "Gestion",
      "Gestion"
    ],
    "labels": [
      "B-Auteur",
      "I-Auteur",
      "I-Auteur",
      "B-Auteur",
      "I-Auteur",
      "I-Auteur",
      "O",
      "B-Auteur",
      "I-Auteur",
      "I-Auteur",
      "B-DatePublication",
      "I-DatePublication",
      "B-Titre",
      "I-Titre",
      "I-Titre",
      "I-Titre",
      "I-Titre",
      "I-Titre",
      "I-Titre",
      "I-Titre",
      "I-Titre",
      "I-Titre",
      "I-Titre",
      "B-TitreRevue",
      "I-TitreRevue",
      "I-TitreRevue",
      "I-TitreRevue",
      "I-TitreRevue"
    ]
  },
  {
    "words": [
      "Cros,",
      "M.",
      "M.",
      "&",
      "Cros,",
      "S.",
      "S.",
      "2015",
      "2015",
      "Le",
      "Management",
      "de",
      "la",
      "communication",
      "de",
      "crise",
      "crise",
      "Management",
      "international",
      "international",
      "20",
      "20",
      "1",
      "1"
    ],
    "labels": [
      "B-Auteur",
      "I-Auteur",
      "I-Auteur",
      "O",
      "B-Auteur",
      "I-Auteur",
      "I-Auteur",
      "B-DatePublication",
      "I-DatePublication",
      "B-Titre",
      "I-Titre",
      "I-Titre",
      "I-Titre",
      "I-Titre",
      "I-Titre",
      "I-Titre",
      "I-Titre",
      "B-TitreRevue",
      "I-TitreRevue",
      "I-TitreRevue",
      "B-Volume",
      "I-Volume",
      "B-Numero",
      "I-Numero"
    ]
  },
  {
    "words": [
      "Badot,",
      "O.",
      "O.",
      "&",
      "Lemoine,",
      "J.",
      "F.",
      "F.",
      "2013",
      "2013",
      "Quels",
      "enseignements",
      "tirer",
      "de",
      "la",
      "s\u00e9rie",
      "tv",
      "Dr",
      "House",
      "pour",
      "l'ethnomarketing?",
      "Vers",
      "un",
      "\u00abethnomarketing",
      "am\u00e9nag\u00e9\u00bb",
      "am\u00e9nag\u00e9\u00bb",
      "Management",
      "&",
      "Avenir",
      "Avenir",
      "3",
      "3"
    ],
    "labels": [
      "B-Auteur",
      "I-Auteur",
      "I-Auteur",
      "O",
      "B-Auteur",
      "I-Auteur",
      "I-Auteur",
      "I-Auteur",
      "B-DatePublication",
      "I-DatePublication",
      "B-Titre",
      "I-Titre",
      "I-Titre",
      "I-Titre",
      "I-Titre",
      "I-Titre",
      "I-Titre",
      "I-Titre",
      "I-Titre",
      "I-Titre",
      "I-Titre",
      "I-Titre",
      "I-Titre",
      "I-Titre",
      "I-Titre",
      "I-Titre",
      "B-TitreRevue",
      "I-TitreRevue",
      "I-TitreRevue",
      "I-TitreRevue",
      "B-Volume",
      "I-Volume"
    ]
  },
  {
    "words": [
      "Baruel",
      "Bencherqui,",
      "D.",
      "D.",
      "&",
      "Kefi,",
      "K.",
      "M.",
      "M.",
      "Renaud,",
      "J.",
      "J.",
      "2013",
      "2013",
      "Satisfaction",
      "de",
      "la",
      "vie",
      "professionnelle,",
      "r\u00e9seaux",
      "sociaux",
      "et",
      "employabilit\u00e9",
      "chez",
      "les",
      "jeunes",
      "salari\u00e9s",
      "de",
      "18/30",
      "ans",
      "ans",
      "Management",
      "&",
      "Avenir",
      "Avenir"
    ],
    "labels": [
      "B-Auteur",
      "I-Auteur",
      "I-Auteur",
      "I-Auteur",
      "O",
      "B-Auteur",
      "I-Auteur",
      "I-Auteur",
      "I-Auteur",
      "B-Auteur",
      "I-Auteur",
      "I-Auteur",
      "B-DatePublication",
      "I-DatePublication",
      "B-Titre",
      "I-Titre",
      "I-Titre",
      "I-Titre",
      "I-Titre",
      "I-Titre",
      "I-Titre",
      "I-Titre",
      "I-Titre",
      "I-Titre",
      "I-Titre",
      "I-Titre",
      "I-Titre",
      "I-Titre",
      "I-Titre",
      "I-Titre",
      "I-Titre",
      "B-TitreRevue",
      "I-TitreRevue",
      "I-TitreRevue",
      "I-TitreRevue"
    ]
  },
  {
    "words": [
      "Chanson,",
      "G.",
      "G.",
      "&",
      "Rouges,",
      "V.",
      "V.",
      "2012",
      "2012",
      "L\u2019externalisation",
      "de",
      "la",
      "fonction",
      "comptable",
      "\u00e0",
      "l\u2019\u00e9preuve",
      "de",
      "la",
      "th\u00e9orie",
      "du",
      "signal",
      "signal"
    ],
    "labels": [
      "B-Auteur",
      "I-Auteur",
      "I-Auteur",
      "O",
      "B-Auteur",
      "I-Auteur",
      "I-Auteur",
      "B-DatePublication",
      "I-DatePublication",
      "B-Titre",
      "I-Titre",
      "I-Titre",
      "I-Titre",
      "I-Titre",
      "I-Titre",
      "I-Titre",
      "I-Titre",
      "I-Titre",
      "I-Titre",
      "I-Titre",
      "I-Titre",
      "I-Titre"
    ]
  },
  {
    "words": [
      "Jacquinot,",
      "P.",
      "P.",
      "&",
      "Pellissier-Tanon,",
      "A.",
      "A.",
      "2012",
      "2012",
      "Sans",
      "rencontre,",
      "quelle",
      "justice",
      "interpersonnelle?",
      "Une",
      "analyse",
      "compr\u00e9hensive",
      "des",
      "blocages",
      "actuels",
      "des",
      "relations",
      "sociales",
      "sociales",
      "@",
      "GRH",
      "GRH",
      "1",
      "1"
    ],
    "labels": [
      "B-Auteur",
      "I-Auteur",
      "I-Auteur",
      "O",
      "B-Auteur",
      "I-Auteur",
      "I-Auteur",
      "B-DatePublication",
      "I-DatePublication",
      "B-Titre",
      "I-Titre",
      "I-Titre",
      "I-Titre",
      "I-Titre",
      "I-Titre",
      "I-Titre",
      "I-Titre",
      "I-Titre",
      "I-Titre",
      "I-Titre",
      "I-Titre",
      "I-Titre",
      "I-Titre",
      "I-Titre",
      "B-TitreRevue",
      "I-TitreRevue",
      "I-TitreRevue",
      "B-Volume",
      "I-Volume"
    ]
  },
  {
    "words": [
      "Lemoine,",
      "J.",
      "F.",
      "F.",
      "&",
      "Cherif,",
      "E.",
      "E.",
      "2012",
      "2012",
      "Comment",
      "g\u00e9n\u00e9rer",
      "de",
      "la",
      "confiance",
      "envers",
      "un",
      "agent",
      "virtuel",
      "\u00e0",
      "l'aide",
      "de",
      "ses",
      "caract\u00e9ristiques?",
      "Une",
      "\u00e9tude",
      "exploratoire",
      "exploratoire",
      "Management",
      "&",
      "Avenir",
      "Avenir",
      "8",
      "8"
    ],
    "labels": [
      "B-Auteur",
      "I-Auteur",
      "I-Auteur",
      "I-Auteur",
      "O",
      "B-Auteur",
      "I-Auteur",
      "I-Auteur",
      "B-DatePublication",
      "I-DatePublication",
      "B-Titre",
      "I-Titre",
      "I-Titre",
      "I-Titre",
      "I-Titre",
      "I-Titre",
      "I-Titre",
      "I-Titre",
      "I-Titre",
      "I-Titre",
      "I-Titre",
      "I-Titre",
      "I-Titre",
      "I-Titre",
      "I-Titre",
      "I-Titre",
      "I-Titre",
      "I-Titre",
      "B-TitreRevue",
      "I-TitreRevue",
      "I-TitreRevue",
      "I-TitreRevue",
      "B-Numero",
      "I-Numero"
    ]
  },
  {
    "words": [
      "Baruel",
      "Bencherqui,",
      "D.",
      "D.",
      "&",
      "Kefi,",
      "M.",
      "K.",
      "K.",
      "2014",
      "2014",
      "Corporate",
      "Competitive",
      "Advantage:",
      "from",
      "organizational",
      "Learning",
      "(absorptive",
      "capacity)",
      "to",
      "Innovation",
      "Innovation",
      "Revue",
      "de",
      "gestion",
      "des",
      "ressources",
      "humaines",
      "humaines",
      "4",
      "4"
    ],
    "labels": [
      "B-Auteur",
      "I-Auteur",
      "I-Auteur",
      "I-Auteur",
      "O",
      "B-Auteur",
      "I-Auteur",
      "I-Auteur",
      "I-Auteur",
      "B-DatePublication",
      "I-DatePublication",
      "B-Titre",
      "I-Titre",
      "I-Titre",
      "I-Titre",
      "I-Titre",
      "I-Titre",
      "I-Titre",
      "I-Titre",
      "I-Titre",
      "I-Titre",
      "I-Titre",
      "B-TitreRevue",
      "I-TitreRevue",
      "I-TitreRevue",
      "I-TitreRevue",
      "I-TitreRevue",
      "I-TitreRevue",
      "I-TitreRevue",
      "B-Volume",
      "I-Volume"
    ]
  },
  {
    "words": [
      "Fr\u00e9ry,",
      "F.",
      "F.",
      "Gratacap,",
      "A.",
      "A.",
      "Isckia,",
      "T.",
      "T.",
      "2012",
      "2012",
      "Les",
      "\u00e9cosyst\u00e8mes",
      "d'affaires,",
      "par-del\u00e0",
      "la",
      "m\u00e9taphore",
      "m\u00e9taphore",
      "Revue",
      "fran\u00e7aise",
      "de",
      "gestion",
      "gestion"
    ],
    "labels": [
      "B-Auteur",
      "I-Auteur",
      "I-Auteur",
      "B-Auteur",
      "I-Auteur",
      "I-Auteur",
      "B-Auteur",
      "I-Auteur",
      "I-Auteur",
      "B-DatePublication",
      "I-DatePublication",
      "B-Titre",
      "I-Titre",
      "I-Titre",
      "I-Titre",
      "I-Titre",
      "I-Titre",
      "I-Titre",
      "B-TitreRevue",
      "I-TitreRevue",
      "I-TitreRevue",
      "I-TitreRevue",
      "I-TitreRevue"
    ]
  },
  {
    "words": [
      "Gratacap,",
      "A.",
      "A.",
      "Isckia,",
      "T.",
      "T.",
      "&",
      "Parisot,",
      "X.",
      "X.",
      "2017",
      "2017",
      "Une",
      "lecture",
      "lakatosienne",
      "de",
      "l'approche",
      "par",
      "les",
      "\u00e9cosyst\u00e8mes",
      "d'affaires",
      "d'affaires",
      "Management",
      "International/International",
      "Management/Gesti\u00f3n",
      "Internacional",
      "Internacional",
      "21",
      "21"
    ],
    "labels": [
      "B-Auteur",
      "I-Auteur",
      "I-Auteur",
      "B-Auteur",
      "I-Auteur",
      "I-Auteur",
      "O",
      "B-Auteur",
      "I-Auteur",
      "I-Auteur",
      "B-DatePublication",
      "I-DatePublication",
      "B-Titre",
      "I-Titre",
      "I-Titre",
      "I-Titre",
      "I-Titre",
      "I-Titre",
      "I-Titre",
      "I-Titre",
      "I-Titre",
      "I-Titre",
      "B-TitreRevue",
      "I-TitreRevue",
      "I-TitreRevue",
      "I-TitreRevue",
      "I-TitreRevue",
      "B-Volume",
      "I-Volume"
    ]
  },
  {
    "words": [
      "Bothorel,",
      "G.",
      "G.",
      "Vanheems,",
      "R.",
      "R.",
      "&",
      "Gu\u00e9rin,",
      "A.",
      "A.",
      "2016",
      "2016",
      "Communication",
      "omnicanal:",
      "comment",
      "orchestrer",
      "num\u00e9rique",
      "et",
      "mobile",
      "pour",
      "g\u00e9n\u00e9rer",
      "de",
      "la",
      "valeur",
      "incr\u00e9mentale",
      "aupr\u00e8s",
      "des",
      "clients",
      "connect\u00e9s?",
      "connect\u00e9s?",
      "D\u00e9cisions",
      "Marketing",
      "Marketing"
    ],
    "labels": [
      "B-Auteur",
      "I-Auteur",
      "I-Auteur",
      "B-Auteur",
      "I-Auteur",
      "I-Auteur",
      "O",
      "B-Auteur",
      "I-Auteur",
      "I-Auteur",
      "B-DatePublication",
      "I-DatePublication",
      "B-Titre",
      "I-Titre",
      "I-Titre",
      "I-Titre",
      "I-Titre",
      "I-Titre",
      "I-Titre",
      "I-Titre",
      "I-Titre",
      "I-Titre",
      "I-Titre",
      "I-Titre",
      "I-Titre",
      "I-Titre",
      "I-Titre",
      "I-Titre",
      "I-Titre",
      "I-Titre",
      "B-TitreRevue",
      "I-TitreRevue",
      "I-TitreRevue"
    ]
  },
  {
    "words": [
      "Greenan,",
      "N.",
      "N.",
      "Narcy,",
      "M.",
      "M.",
      "&",
      "Robin,",
      "S.",
      "S.",
      "2012",
      "2012",
      "Changements",
      "au",
      "sein",
      "des",
      "entreprises",
      "et",
      "acc\u00e8s",
      "des",
      "seniors",
      "\u00e0",
      "la",
      "formation",
      "continue",
      "dans",
      "les",
      "ann\u00e9es",
      "1990",
      "et",
      "2000",
      "2000",
      "Revue",
      "fran\u00e7aise",
      "d'\u00e9conomie",
      "d'\u00e9conomie"
    ],
    "labels": [
      "B-Auteur",
      "I-Auteur",
      "I-Auteur",
      "B-Auteur",
      "I-Auteur",
      "I-Auteur",
      "O",
      "B-Auteur",
      "I-Auteur",
      "I-Auteur",
      "B-DatePublication",
      "I-DatePublication",
      "B-Titre",
      "I-Titre",
      "I-Titre",
      "I-Titre",
      "I-Titre",
      "I-Titre",
      "I-Titre",
      "I-Titre",
      "I-Titre",
      "I-Titre",
      "I-Titre",
      "I-Titre",
      "I-Titre",
      "I-Titre",
      "I-Titre",
      "I-Titre",
      "I-Titre",
      "I-Titre",
      "I-Titre",
      "I-Titre",
      "B-TitreRevue",
      "I-TitreRevue",
      "I-TitreRevue",
      "I-TitreRevue"
    ]
  },
  {
    "words": [
      "Le",
      "Flanchec,",
      "A.",
      "A.",
      "Mullenbach",
      "Servayre,",
      "A.",
      "A.",
      "&",
      "Rojot,",
      "J.",
      "J.",
      "2017",
      "2017",
      "Pratiques",
      "de",
      "GRH",
      "et",
      "strat\u00e9gies",
      "d\u2019innovation:",
      "les",
      "apports",
      "de",
      "l\u2019enqu\u00eate",
      "REPONSE",
      "2011",
      "2011",
      "Relations",
      "Industrielles",
      "/",
      "Industrial",
      "Relations",
      "Relations"
    ],
    "labels": [
      "B-Auteur",
      "I-Auteur",
      "I-Auteur",
      "I-Auteur",
      "B-Auteur",
      "I-Auteur",
      "I-Auteur",
      "I-Auteur",
      "O",
      "B-Auteur",
      "I-Auteur",
      "I-Auteur",
      "B-DatePublication",
      "I-DatePublication",
      "B-Titre",
      "I-Titre",
      "I-Titre",
      "I-Titre",
      "I-Titre",
      "I-Titre",
      "I-Titre",
      "I-Titre",
      "I-Titre",
      "I-Titre",
      "I-Titre",
      "I-Titre",
      "I-Titre",
      "B-TitreRevue",
      "I-TitreRevue",
      "I-TitreRevue",
      "I-TitreRevue",
      "I-TitreRevue",
      "I-TitreRevue"
    ]
  },
  {
    "words": [
      "Badot,",
      "O.",
      "O.",
      "&",
      "Lemoine,",
      "J.",
      "F.",
      "F.",
      "2013",
      "2013",
      "Du",
      "paradigme",
      "dichotomique",
      "de",
      "l\u2019exp\u00e9rience",
      "d\u2019achat",
      "au",
      "paradigme",
      "ubiquitaire",
      "ubiquitaire",
      "Recherche",
      "et",
      "Applications",
      "en",
      "Marketing",
      "Marketing",
      "Vol.",
      "28",
      "28",
      "3",
      "3",
      "3-13",
      "3-13"
    ],
    "labels": [
      "B-Auteur",
      "I-Auteur",
      "I-Auteur",
      "O",
      "B-Auteur",
      "I-Auteur",
      "I-Auteur",
      "I-Auteur",
      "B-DatePublication",
      "I-DatePublication",
      "B-Titre",
      "I-Titre",
      "I-Titre",
      "I-Titre",
      "I-Titre",
      "I-Titre",
      "I-Titre",
      "I-Titre",
      "I-Titre",
      "I-Titre",
      "B-TitreRevue",
      "I-TitreRevue",
      "I-TitreRevue",
      "I-TitreRevue",
      "I-TitreRevue",
      "I-TitreRevue",
      "O",
      "B-Volume",
      "I-Volume",
      "B-Numero",
      "I-Numero",
      "B-Pages",
      "I-Pages"
    ]
  },
  {
    "words": [
      "Chanson,",
      "G.",
      "G.",
      "2014",
      "2014",
      "Externalisation",
      "et",
      "th\u00e9orie",
      "des",
      "co\u00fbts",
      "de",
      "transaction:",
      "analyser",
      "un",
      "ph\u00e9nom\u00e8ne",
      "dynamique",
      "avec",
      "une",
      "th\u00e9orie",
      "statique?",
      "statique?",
      "Management",
      "international/International",
      "Management/Gesti\u00f2n",
      "Internacional",
      "Internacional"
    ],
    "labels": [
      "B-Auteur",
      "I-Auteur",
      "I-Auteur",
      "B-DatePublication",
      "I-DatePublication",
      "B-Titre",
      "I-Titre",
      "I-Titre",
      "I-Titre",
      "I-Titre",
      "I-Titre",
      "I-Titre",
      "I-Titre",
      "I-Titre",
      "I-Titre",
      "I-Titre",
      "I-Titre",
      "I-Titre",
      "I-Titre",
      "I-Titre",
      "I-Titre",
      "B-TitreRevue",
      "I-TitreRevue",
      "I-TitreRevue",
      "I-TitreRevue",
      "I-TitreRevue"
    ]
  },
  {
    "words": [
      "Legalais,",
      "L.",
      "L.",
      "&",
      "Morales,",
      "J.",
      "J.",
      "2014)",
      "2014)",
      "Interfaces,",
      "narrations",
      "et",
      "l\u00e9gitimation",
      "de",
      "la",
      "financiarisation",
      "financiarisation",
      "Revue",
      "fran\u00e7aise",
      "de",
      "gestion",
      "gestion",
      "3",
      "3"
    ],
    "labels": [
      "B-Auteur",
      "I-Auteur",
      "I-Auteur",
      "O",
      "B-DatePublication",
      "I-DatePublication",
      "I-DatePublication",
      "B-Titre",
      "I-Titre",
      "B-TitreRevue",
      "I-TitreRevue",
      "I-TitreRevue",
      "I-TitreRevue",
      "I-TitreRevue",
      "I-TitreRevue",
      "I-TitreRevue",
      "I-TitreRevue",
      "B-Volume",
      "I-Volume",
      "I-Volume",
      "I-Volume",
      "I-Volume",
      "B-Numero",
      "I-Numero"
    ]
  },
  {
    "words": [
      "Cloet,",
      "H.",
      "H.",
      "&",
      "Vernazobres,",
      "P.",
      "P.",
      "2012",
      "2012",
      "La",
      "place",
      "du",
      "coaching",
      "dans",
      "l'accompagnement",
      "de",
      "l'entrepreneuriat:",
      "l'\u00e9volution",
      "des",
      "id\u00e9es",
      "et",
      "des",
      "pratiques",
      "en",
      "France,",
      "sa",
      "traduction",
      "dans",
      "les",
      "faits",
      "en",
      "Languedoc-Roussillon",
      "Languedoc-Roussillon",
      "Management",
      "&",
      "Avenir",
      "Avenir",
      "3",
      "3",
      "121-141",
      "121-141"
    ],
    "labels": [
      "B-Auteur",
      "I-Auteur",
      "I-Auteur",
      "O",
      "B-Auteur",
      "I-Auteur",
      "I-Auteur",
      "B-DatePublication",
      "I-DatePublication",
      "B-Titre",
      "I-Titre",
      "I-Titre",
      "I-Titre",
      "I-Titre",
      "I-Titre",
      "I-Titre",
      "I-Titre",
      "I-Titre",
      "I-Titre",
      "I-Titre",
      "I-Titre",
      "I-Titre",
      "I-Titre",
      "I-Titre",
      "I-Titre",
      "I-Titre",
      "I-Titre",
      "I-Titre",
      "I-Titre",
      "I-Titre",
      "I-Titre",
      "I-Titre",
      "I-Titre",
      "B-TitreRevue",
      "I-TitreRevue",
      "I-TitreRevue",
      "I-TitreRevue",
      "B-Volume",
      "I-Volume",
      "B-Pages",
      "I-Pages"
    ]
  },
  {
    "words": [
      "Combe,",
      "E.",
      "E.",
      "&",
      "Monnier,",
      "C.",
      "C.",
      "2012",
      "2012",
      "Les",
      "cartels",
      "en",
      "Europe,",
      "une",
      "analyse",
      "empirique",
      "empirique",
      "Revue",
      "fran\u00e7aise",
      "d'\u00e9conomie",
      "d'\u00e9conomie"
    ],
    "labels": [
      "B-Auteur",
      "I-Auteur",
      "I-Auteur",
      "O",
      "B-Auteur",
      "I-Auteur",
      "I-Auteur",
      "B-DatePublication",
      "I-DatePublication",
      "B-Titre",
      "I-Titre",
      "I-Titre",
      "I-Titre",
      "I-Titre",
      "I-Titre",
      "I-Titre",
      "I-Titre",
      "B-TitreRevue",
      "I-TitreRevue",
      "I-TitreRevue",
      "I-TitreRevue"
    ]
  },
  {
    "words": [
      "Kilic,",
      "S.",
      "S.",
      "2014",
      "2014",
      "Perception",
      "de",
      "l'\u00e9quilibre",
      "travail\u2013hors-travail",
      "et",
      "satisfaction",
      "au",
      "travail",
      "travail",
      "Management",
      "&",
      "Avenir",
      "Avenir",
      "3",
      "3",
      "89-105",
      "89-105"
    ],
    "labels": [
      "B-Auteur",
      "I-Auteur",
      "I-Auteur",
      "B-DatePublication",
      "I-DatePublication",
      "B-Titre",
      "I-Titre",
      "I-Titre",
      "I-Titre",
      "I-Titre",
      "I-Titre",
      "I-Titre",
      "I-Titre",
      "I-Titre",
      "B-TitreRevue",
      "I-TitreRevue",
      "I-TitreRevue",
      "I-TitreRevue",
      "B-Volume",
      "I-Volume",
      "B-Pages",
      "I-Pages"
    ]
  },
  {
    "words": [
      "Damay,",
      "C.",
      "C.",
      "&",
      "Guichard,",
      "N.",
      "N.",
      "2016",
      "2016",
      "La",
      "place",
      "du",
      "prix",
      "dans",
      "la",
      "socialisation",
      "de",
      "l\u2019enfant-consommateur",
      "l\u2019enfant-consommateur",
      "Recherche",
      "et",
      "Applications",
      "en",
      "Marketing",
      "(French",
      "Edition)",
      "Edition)"
    ],
    "labels": [
      "B-Auteur",
      "I-Auteur",
      "I-Auteur",
      "O",
      "B-Auteur",
      "I-Auteur",
      "I-Auteur",
      "B-DatePublication",
      "I-DatePublication",
      "B-Titre",
      "I-Titre",
      "I-Titre",
      "I-Titre",
      "I-Titre",
      "I-Titre",
      "I-Titre",
      "I-Titre",
      "I-Titre",
      "I-Titre",
      "B-TitreRevue",
      "I-TitreRevue",
      "I-TitreRevue",
      "I-TitreRevue",
      "I-TitreRevue",
      "I-TitreRevue",
      "I-TitreRevue",
      "I-TitreRevue"
    ]
  },
  {
    "words": [
      "Fleckinger,",
      "P.",
      "P.",
      "Lafay,",
      "T.",
      "T.",
      "&",
      "Monnier,",
      "C.",
      "C.",
      "2013",
      "2013",
      "R\u00e9mun\u00e9ration",
      "des",
      "dirigeants",
      "et",
      "risque",
      "de",
      "fraude",
      "d'entreprise",
      "d'entreprise",
      "Revue",
      "\u00e9conomique",
      "\u00e9conomique"
    ],
    "labels": [
      "B-Auteur",
      "I-Auteur",
      "I-Auteur",
      "B-Auteur",
      "I-Auteur",
      "I-Auteur",
      "O",
      "B-Auteur",
      "I-Auteur",
      "I-Auteur",
      "B-DatePublication",
      "I-DatePublication",
      "B-Titre",
      "I-Titre",
      "I-Titre",
      "I-Titre",
      "I-Titre",
      "I-Titre",
      "I-Titre",
      "I-Titre",
      "I-Titre",
      "B-TitreRevue",
      "I-TitreRevue",
      "I-TitreRevue"
    ]
  },
  {
    "words": [
      "Baruel",
      "Bencherqui,",
      "D.",
      "D.",
      "Kefi,",
      "M.",
      "K.",
      "K.",
      "Le",
      "Flanchec,",
      "A.",
      "A.",
      "&",
      "Servayre,",
      "A.",
      "M.",
      "M.",
      "2012",
      "2012",
      "L'employabilit\u00e9",
      "et",
      "son",
      "r\u00f4le",
      "sur",
      "la",
      "satisfaction,",
      "la",
      "formation",
      "et",
      "les",
      "r\u00e9seaux",
      "sociaux",
      "sociaux",
      "Recherches",
      "en",
      "sciences",
      "de",
      "gestion",
      "gestion",
      "5",
      "5"
    ],
    "labels": [
      "B-Auteur",
      "I-Auteur",
      "I-Auteur",
      "I-Auteur",
      "B-Auteur",
      "I-Auteur",
      "I-Auteur",
      "I-Auteur",
      "B-Auteur",
      "I-Auteur",
      "I-Auteur",
      "I-Auteur",
      "O",
      "B-Auteur",
      "I-Auteur",
      "I-Auteur",
      "I-Auteur",
      "B-DatePublication",
      "I-DatePublication",
      "B-Titre",
      "I-Titre",
      "I-Titre",
      "I-Titre",
      "I-Titre",
      "I-Titre",
      "I-Titre",
      "I-Titre",
      "I-Titre",
      "I-Titre",
      "I-Titre",
      "I-Titre",
      "I-Titre",
      "I-Titre",
      "B-TitreRevue",
      "I-TitreRevue",
      "I-TitreRevue",
      "I-TitreRevue",
      "I-TitreRevue",
      "I-TitreRevue",
      "B-Volume",
      "I-Volume"
    ]
  },
  {
    "words": [
      "Bouzid,",
      "Y.",
      "Y.",
      "&",
      "Vanheems,",
      "R.",
      "R.",
      "2014",
      "2014",
      "Comportement",
      "web-to-store:",
      "vers",
      "une",
      "nouvelle",
      "logique",
      "de",
      "contr\u00f4le",
      "de",
      "soi?",
      "soi?",
      "Management",
      "&",
      "Avenir",
      "Avenir",
      "5",
      "5"
    ],
    "labels": [
      "B-Auteur",
      "I-Auteur",
      "I-Auteur",
      "O",
      "B-Auteur",
      "I-Auteur",
      "I-Auteur",
      "B-DatePublication",
      "I-DatePublication",
      "B-Titre",
      "I-Titre",
      "I-Titre",
      "I-Titre",
      "I-Titre",
      "I-Titre",
      "I-Titre",
      "I-Titre",
      "I-Titre",
      "I-Titre",
      "I-Titre",
      "B-TitreRevue",
      "I-TitreRevue",
      "I-TitreRevue",
      "I-TitreRevue",
      "B-Volume",
      "I-Volume"
    ]
  },
  {
    "words": [
      "Chanson,",
      "G.",
      "G.",
      "&",
      "Rouges,",
      "V.",
      "V.",
      "2012",
      "2012",
      "L\u2019externalisation",
      "de",
      "la",
      "fonction",
      "comptable",
      "\u00e0",
      "l\u2019\u00e9preuve",
      "de",
      "la",
      "th\u00e9orie",
      "du",
      "signal",
      "signal",
      "Finance",
      "Contr\u00f4le",
      "Strat\u00e9gie",
      "Strat\u00e9gie",
      "15",
      "15"
    ],
    "labels": [
      "B-Auteur",
      "I-Auteur",
      "I-Auteur",
      "O",
      "B-Auteur",
      "I-Auteur",
      "I-Auteur",
      "B-DatePublication",
      "I-DatePublication",
      "B-Titre",
      "I-Titre",
      "I-Titre",
      "I-Titre",
      "I-Titre",
      "I-Titre",
      "I-Titre",
      "I-Titre",
      "I-Titre",
      "I-Titre",
      "I-Titre",
      "I-Titre",
      "I-Titre",
      "B-TitreRevue",
      "I-TitreRevue",
      "I-TitreRevue",
      "I-TitreRevue",
      "B-Volume",
      "I-Volume"
    ]
  },
  {
    "words": [
      "Drucker-Godard,",
      "C.",
      "C.",
      "Fouque,",
      "T.",
      "T.",
      "Gollety,",
      "M.",
      "M.",
      "&",
      "Le",
      "Flanchec,",
      "A.",
      "A.",
      "2013",
      "2013",
      "Le",
      "ressenti",
      "des",
      "enseignants-chercheurs:",
      "un",
      "conflit",
      "de",
      "valeurs",
      "valeurs",
      "Gestion",
      "et",
      "management",
      "public",
      "public"
    ],
    "labels": [
      "B-Auteur",
      "I-Auteur",
      "I-Auteur",
      "B-Auteur",
      "I-Auteur",
      "I-Auteur",
      "B-Auteur",
      "I-Auteur",
      "I-Auteur",
      "O",
      "B-Auteur",
      "I-Auteur",
      "I-Auteur",
      "I-Auteur",
      "B-DatePublication",
      "I-DatePublication",
      "B-Titre",
      "I-Titre",
      "I-Titre",
      "I-Titre",
      "I-Titre",
      "I-Titre",
      "I-Titre",
      "I-Titre",
      "I-Titre",
      "B-TitreRevue",
      "I-TitreRevue",
      "I-TitreRevue",
      "I-TitreRevue",
      "I-TitreRevue"
    ]
  },
  {
    "words": [
      "Ezan,",
      "P.",
      "P.",
      "Gollety,",
      "M.",
      "M.",
      "Guichard,",
      "N.",
      "N.",
      "&",
      "H\u00e9mar-Nicolas,",
      "V.",
      "V.",
      "(2014",
      "(2014",
      "Renforcer",
      "l'efficacit\u00e9",
      "des",
      "actions",
      "de",
      "lutte",
      "contre",
      "l'ob\u00e9sit\u00e9.",
      "Vers",
      "l'identification",
      "de",
      "leviers",
      "de",
      "persuasion",
      "sp\u00e9cifiques",
      "aux",
      "enfants",
      "enfants",
      "D\u00e9cisions",
      "Marketing",
      "Marketing",
      "(73",
      "(73"
    ],
    "labels": [
      "B-Auteur",
      "I-Auteur",
      "I-Auteur",
      "B-Auteur",
      "I-Auteur",
      "I-Auteur",
      "B-Auteur",
      "I-Auteur",
      "I-Auteur",
      "O",
      "B-Auteur",
      "I-Auteur",
      "I-Auteur",
      "B-DatePublication",
      "I-DatePublication",
      "B-Titre",
      "I-Titre",
      "I-Titre",
      "I-Titre",
      "I-Titre",
      "I-Titre",
      "I-Titre",
      "I-Titre",
      "I-Titre",
      "I-Titre",
      "I-Titre",
      "I-Titre",
      "I-Titre",
      "I-Titre",
      "I-Titre",
      "I-Titre",
      "I-Titre",
      "I-Titre",
      "B-TitreRevue",
      "I-TitreRevue",
      "I-TitreRevue",
      "B-Volume",
      "I-Volume"
    ]
  },
  {
    "words": [
      "Janand,",
      "A.",
      "A.",
      "Guettiche,",
      "F",
      "F",
      "&",
      "Cloet,",
      "H.",
      "H.",
      "2016",
      "2016",
      "Le",
      "management",
      "\u00abeurop\u00e9en\u00bb",
      "des",
      "talents:",
      "au-del\u00e0",
      "des",
      "typologies",
      "existantes",
      "existantes",
      "Revue",
      "de",
      "gestion",
      "des",
      "ressources",
      "humaines",
      "humaines"
    ],
    "labels": [
      "B-Auteur",
      "I-Auteur",
      "I-Auteur",
      "B-Auteur",
      "I-Auteur",
      "I-Auteur",
      "O",
      "B-Auteur",
      "I-Auteur",
      "I-Auteur",
      "B-DatePublication",
      "I-DatePublication",
      "B-Titre",
      "I-Titre",
      "I-Titre",
      "I-Titre",
      "I-Titre",
      "I-Titre",
      "I-Titre",
      "I-Titre",
      "I-Titre",
      "I-Titre",
      "B-TitreRevue",
      "I-TitreRevue",
      "I-TitreRevue",
      "I-TitreRevue",
      "I-TitreRevue",
      "I-TitreRevue",
      "I-TitreRevue"
    ]
  },
  {
    "words": [
      "Karakas,",
      "S.",
      "S.",
      "2016",
      "2016",
      "Les",
      "valeurs",
      "professionnelles",
      "et",
      "les",
      "pr\u00e9f\u00e9rences",
      "quant",
      "au",
      "choix",
      "de",
      "poste:",
      "une",
      "analyse",
      "des",
      "cadres",
      "\u00e0",
      "potentiel",
      "potentiel",
      "Management",
      "&",
      "Avenir",
      "Avenir",
      "4",
      "4"
    ],
    "labels": [
      "B-Auteur",
      "I-Auteur",
      "I-Auteur",
      "B-DatePublication",
      "I-DatePublication",
      "B-Titre",
      "I-Titre",
      "I-Titre",
      "I-Titre",
      "I-Titre",
      "I-Titre",
      "I-Titre",
      "I-Titre",
      "I-Titre",
      "I-Titre",
      "I-Titre",
      "I-Titre",
      "I-Titre",
      "I-Titre",
      "I-Titre",
      "I-Titre",
      "I-Titre",
      "I-Titre",
      "B-TitreRevue",
      "I-TitreRevue",
      "I-TitreRevue",
      "I-TitreRevue",
      "B-Volume",
      "I-Volume"
    ]
  },
  {
    "words": [
      "Le",
      "Saout,",
      "E.",
      "E.",
      "2015",
      "2015",
      "Carbon",
      "pooling",
      "ou",
      "comment",
      "g\u00e9rer",
      "les",
      "cr\u00e9dits",
      "carbone",
      "\u00e0",
      "partir",
      "d\u2019une",
      "tr\u00e9sorerie",
      "centralis\u00e9e",
      "centralis\u00e9e",
      "Recherches",
      "en",
      "Sciences",
      "de",
      "Gestion",
      "Gestion",
      "3",
      "3",
      "91-112",
      "91-112"
    ],
    "labels": [
      "B-Auteur",
      "I-Auteur",
      "I-Auteur",
      "I-Auteur",
      "B-DatePublication",
      "I-DatePublication",
      "B-DatePublication",
      "I-DatePublication",
      "I-DatePublication",
      "I-DatePublication",
      "I-DatePublication",
      "I-DatePublication",
      "I-DatePublication",
      "I-DatePublication",
      "I-DatePublication",
      "I-DatePublication",
      "I-DatePublication",
      "I-DatePublication",
      "I-DatePublication",
      "I-DatePublication",
      "B-Titre",
      "I-Titre",
      "I-Titre",
      "I-Titre",
      "I-Titre",
      "I-Titre",
      "B-TitreRevue",
      "I-TitreRevue",
      "B-Pages",
      "I-Pages"
    ]
  },
  {
    "words": [
      "Pluchart,",
      "J.",
      "J.",
      "J.",
      "&",
      "Barbara,",
      "L.",
      "L.",
      "2014",
      "2014",
      "Vers",
      "une",
      "approche",
      "constructionniste",
      "du",
      "processus",
      "d'\u00e9valuation",
      "de",
      "l'entreprise",
      "l'entreprise",
      "Recherches",
      "en",
      "Sciences",
      "de",
      "Gestion",
      "Gestion",
      "1",
      "1"
    ],
    "labels": [
      "B-Auteur",
      "I-Auteur",
      "I-Auteur",
      "I-Auteur",
      "O",
      "B-Auteur",
      "I-Auteur",
      "I-Auteur",
      "B-DatePublication",
      "I-DatePublication",
      "B-Titre",
      "I-Titre",
      "I-Titre",
      "I-Titre",
      "I-Titre",
      "I-Titre",
      "I-Titre",
      "I-Titre",
      "I-Titre",
      "I-Titre",
      "B-TitreRevue",
      "I-TitreRevue",
      "I-TitreRevue",
      "I-TitreRevue",
      "I-TitreRevue",
      "I-TitreRevue",
      "B-Volume",
      "I-Volume"
    ]
  },
  {
    "words": [
      "Clauzel,",
      "A.",
      "A.",
      "&",
      "Montargot,",
      "N.",
      "N.",
      "2013",
      "2013",
      "Recommandations",
      "en",
      "ligne",
      "et",
      "place",
      "du",
      "personnel",
      "en",
      "contact.",
      "le",
      "cas",
      "des",
      "produits",
      "h\u00f4teliers",
      "h\u00f4teliers",
      "Revue",
      "Fran\u00e7aise",
      "du",
      "Marketing",
      "Marketing",
      "241",
      "241"
    ],
    "labels": [
      "B-Auteur",
      "I-Auteur",
      "I-Auteur",
      "O",
      "B-Auteur",
      "I-Auteur",
      "I-Auteur",
      "B-DatePublication",
      "I-DatePublication",
      "B-Titre",
      "I-Titre",
      "I-Titre",
      "I-Titre",
      "I-Titre",
      "I-Titre",
      "I-Titre",
      "I-Titre",
      "I-Titre",
      "I-Titre",
      "I-Titre",
      "I-Titre",
      "I-Titre",
      "I-Titre",
      "I-Titre",
      "B-TitreRevue",
      "I-TitreRevue",
      "I-TitreRevue",
      "I-TitreRevue",
      "I-TitreRevue",
      "B-Volume",
      "I-Volume"
    ]
  },
  {
    "words": [
      "Jacquinot,",
      "P.",
      "P.",
      "&",
      "Pellissier-Tanon,",
      "A.",
      "A.",
      "2014",
      "2014",
      "Faire",
      "son",
      "deuil,",
      "susciter",
      "de",
      "la",
      "joie:",
      "un",
      "processus",
      "de",
      "partage",
      "social",
      "d'\u00e9motions",
      "positives-Les",
      "le\u00e7ons",
      "de",
      "l'int\u00e9gration",
      "de",
      "personnes",
      "handicap\u00e9es",
      "en",
      "mati\u00e8re",
      "de",
      "coh\u00e9sion",
      "d'\u00e9quipe",
      "d'\u00e9quipe",
      "RIMHE:",
      "Revue",
      "Interdisciplinaire",
      "Management,",
      "Homme",
      "&",
      "Entreprise",
      "Entreprise",
      "3",
      "3"
    ],
    "labels": [
      "B-Auteur",
      "I-Auteur",
      "I-Auteur",
      "O",
      "B-Auteur",
      "I-Auteur",
      "I-Auteur",
      "B-DatePublication",
      "I-DatePublication",
      "B-Titre",
      "I-Titre",
      "I-Titre",
      "I-Titre",
      "I-Titre",
      "I-Titre",
      "I-Titre",
      "I-Titre",
      "I-Titre",
      "I-Titre",
      "I-Titre",
      "I-Titre",
      "I-Titre",
      "I-Titre",
      "I-Titre",
      "I-Titre",
      "I-Titre",
      "I-Titre",
      "I-Titre",
      "I-Titre",
      "I-Titre",
      "I-Titre",
      "I-Titre",
      "I-Titre",
      "I-Titre",
      "I-Titre",
      "B-TitreRevue",
      "I-TitreRevue",
      "I-TitreRevue",
      "I-TitreRevue",
      "I-TitreRevue",
      "I-TitreRevue",
      "I-TitreRevue",
      "I-TitreRevue",
      "B-Volume",
      "I-Volume"
    ]
  },
  {
    "words": [
      "Lombardot,",
      "E.",
      "E.",
      "&",
      "Mugel,",
      "O.",
      "O.",
      "2017",
      "2017",
      "Proposition",
      "d\u2019un",
      "mod\u00e8le",
      "explicatif",
      "de",
      "l\u2019\u00e9cart",
      "entre",
      "intention",
      "et",
      "comportement",
      "responsable",
      "en",
      "contexte",
      "d\u2019achat",
      "alimentaire",
      "alimentaire",
      "Revue",
      "de",
      "l\u2019organisation",
      "responsable",
      "responsable",
      "12",
      "12",
      "1",
      "1"
    ],
    "labels": [
      "B-Auteur",
      "I-Auteur",
      "I-Auteur",
      "O",
      "B-Auteur",
      "I-Auteur",
      "I-Auteur",
      "B-DatePublication",
      "I-DatePublication",
      "B-Titre",
      "I-Titre",
      "I-Titre",
      "I-Titre",
      "I-Titre",
      "I-Titre",
      "I-Titre",
      "I-Titre",
      "I-Titre",
      "I-Titre",
      "I-Titre",
      "I-Titre",
      "I-Titre",
      "I-Titre",
      "I-Titre",
      "I-Titre",
      "B-TitreRevue",
      "I-TitreRevue",
      "I-TitreRevue",
      "I-TitreRevue",
      "I-TitreRevue",
      "B-Volume",
      "I-Volume",
      "B-Numero",
      "I-Numero"
    ]
  },
  {
    "words": [
      "Pluchart,",
      "J.",
      "J.",
      "J.",
      "2012",
      "2012",
      "L'accompagnement",
      "entrepreneurial.\u00a0Revue",
      "internationale",
      "de",
      "psychosociologie",
      "et",
      "de",
      "gestion",
      "des",
      "comportements",
      "organisationnels",
      "organisationnels",
      "18",
      "18"
    ],
    "labels": [
      "B-Auteur",
      "I-Auteur",
      "I-Auteur",
      "I-Auteur",
      "B-DatePublication",
      "I-DatePublication",
      "B-Titre",
      "I-Titre",
      "I-Titre",
      "I-Titre",
      "I-Titre",
      "I-Titre",
      "I-Titre",
      "I-Titre",
      "I-Titre",
      "I-Titre",
      "I-Titre",
      "I-Titre",
      "B-TitreRevue",
      "I-TitreRevue"
    ]
  },
  {
    "words": [
      "de",
      "La",
      "Robertie,",
      "C.",
      "C.",
      "2014",
      "2014",
      "L\u2019Agence",
      "universitaire",
      "de",
      "la",
      "francophonie",
      ":",
      "pour",
      "une",
      "strat\u00e9gie",
      "d\u2019influence",
      "culturelle",
      "culturelle",
      "Revue",
      "Politique",
      "et",
      "Parlementaire",
      "Parlementaire",
      "(AERES",
      "Droit),",
      "116",
      "116",
      "ann\u00e9e,",
      "N\u00b0",
      "1070",
      "1070",
      "janvier-mars",
      "2014",
      "2014",
      "44-47",
      "44-47"
    ],
    "labels": [
      "B-Auteur",
      "I-Auteur",
      "I-Auteur",
      "I-Auteur",
      "I-Auteur",
      "B-DatePublication",
      "I-DatePublication",
      "B-Titre",
      "I-Titre",
      "I-Titre",
      "I-Titre",
      "I-Titre",
      "I-Titre",
      "I-Titre",
      "I-Titre",
      "I-Titre",
      "I-Titre",
      "I-Titre",
      "I-Titre",
      "B-TitreRevue",
      "I-TitreRevue",
      "I-TitreRevue",
      "I-TitreRevue",
      "I-TitreRevue",
      "O",
      "O",
      "B-Volume",
      "I-Volume",
      "O",
      "O",
      "B-Numero",
      "I-Numero",
      "B-DatePublication",
      "I-DatePublication",
      "I-DatePublication",
      "B-Pages",
      "I-Pages"
    ]
  },
  {
    "words": [
      "Miltgen,",
      "C.",
      "L.",
      "L.",
      "&",
      "Lemoine,",
      "J.",
      "F.",
      "F.",
      "2015",
      "2015",
      "Mieux",
      "collecter",
      "les",
      "donn\u00e9es",
      "personnelles",
      "sur",
      "Internet",
      "Une",
      "\u00e9tude",
      "qualitative",
      "aupr\u00e8s",
      "d'internautes",
      "fran\u00e7ais",
      "fran\u00e7ais",
      "Decisions",
      "Marketing",
      "Marketing"
    ],
    "labels": [
      "B-Auteur",
      "I-Auteur",
      "I-Auteur",
      "I-Auteur",
      "O",
      "B-Auteur",
      "I-Auteur",
      "I-Auteur",
      "I-Auteur",
      "B-DatePublication",
      "I-DatePublication",
      "B-Titre",
      "I-Titre",
      "I-Titre",
      "I-Titre",
      "I-Titre",
      "I-Titre",
      "I-Titre",
      "I-Titre",
      "I-Titre",
      "I-Titre",
      "I-Titre",
      "I-Titre",
      "I-Titre",
      "I-Titre",
      "B-TitreRevue",
      "I-TitreRevue",
      "I-TitreRevue"
    ]
  },
  {
    "words": [
      "Pommet,",
      "S.",
      "S.",
      "&",
      "Sattin,",
      "J.",
      "F.",
      "F.",
      "2012",
      "2012",
      "L\u2019influence",
      "des",
      "strat\u00e9gies",
      "des",
      "soci\u00e9t\u00e9s",
      "de",
      "capital-risque",
      "sur",
      "la",
      "performance",
      "de",
      "leurs",
      "investissements",
      "en",
      "Europe",
      "Europe",
      "Finance",
      "Contr\u00f4le",
      "Strat\u00e9gie",
      "Strat\u00e9gie"
    ],
    "labels": [
      "B-Auteur",
      "I-Auteur",
      "I-Auteur",
      "O",
      "B-Auteur",
      "I-Auteur",
      "I-Auteur",
      "I-Auteur",
      "B-DatePublication",
      "I-DatePublication",
      "B-Titre",
      "I-Titre",
      "I-Titre",
      "I-Titre",
      "I-Titre",
      "I-Titre",
      "I-Titre",
      "I-Titre",
      "I-Titre",
      "I-Titre",
      "I-Titre",
      "I-Titre",
      "I-Titre",
      "I-Titre",
      "I-Titre",
      "I-Titre",
      "B-TitreRevue",
      "I-TitreRevue",
      "I-TitreRevue",
      "I-TitreRevue"
    ]
  },
  {
    "words": [
      "Sattin,",
      "J.",
      "F.",
      "F.",
      "2013",
      "2013",
      "La",
      "licence",
      "d\u00e9fensive:",
      "Une",
      "option",
      "strat\u00e9gique",
      "pour",
      "les",
      "PME",
      "innovantes?",
      "innovantes?",
      "Revue",
      "internationale",
      "PME",
      "PME"
    ],
    "labels": [
      "B-Auteur",
      "I-Auteur",
      "I-Auteur",
      "I-Auteur",
      "B-DatePublication",
      "I-DatePublication",
      "B-Titre",
      "I-Titre",
      "I-Titre",
      "I-Titre",
      "I-Titre",
      "I-Titre",
      "I-Titre",
      "I-Titre",
      "I-Titre",
      "I-Titre",
      "I-Titre",
      "B-Titre",
      "I-Titre",
      "I-Titre",
      "I-Titre"
    ]
  },
  {
    "words": [
      "Bontour,",
      "A.",
      "A.",
      "2015",
      "2015",
      "L\u2019estime",
      "de",
      "soi:",
      "un",
      "facteur",
      "individuel",
      "pour",
      "mieux",
      "penser",
      "sa",
      "relation",
      "client?",
      "client?",
      "La",
      "Revue",
      "des",
      "Sciences",
      "de",
      "Gestion",
      "Gestion",
      "5",
      "5"
    ],
    "labels": [
      "B-Auteur",
      "I-Auteur",
      "I-Auteur",
      "B-DatePublication",
      "I-DatePublication",
      "B-Titre",
      "I-Titre",
      "I-Titre",
      "I-Titre",
      "I-Titre",
      "I-Titre",
      "I-Titre",
      "I-Titre",
      "I-Titre",
      "I-Titre",
      "I-Titre",
      "I-Titre",
      "I-Titre",
      "B-TitreRevue",
      "I-TitreRevue",
      "I-TitreRevue",
      "I-TitreRevue",
      "I-TitreRevue",
      "I-TitreRevue",
      "I-TitreRevue",
      "B-Volume",
      "I-Volume"
    ]
  },
  {
    "words": [
      "Clauzel,",
      "A.",
      "A.",
      "et",
      "Rich\u00e9,",
      "C.",
      "C.",
      "2016",
      "2016",
      "Quand",
      "le",
      "consommateur",
      "partage",
      "son",
      "avis",
      "en",
      "ligne",
      ":",
      "une",
      "approche",
      "comparative",
      "en",
      "h\u00f4tellerie",
      "et",
      "restauration",
      ":",
      "Le",
      "cas",
      "des",
      "seniors",
      "seniors",
      "La",
      "Revue",
      "des",
      "Sciences",
      "de",
      "Gestion,",
      "Direction",
      "et",
      "Gestion",
      "Gestion",
      "Forthcoming",
      "Forthcoming"
    ],
    "labels": [
      "B-Auteur",
      "I-Auteur",
      "I-Auteur",
      "O",
      "B-Auteur",
      "I-Auteur",
      "I-Auteur",
      "B-DatePublication",
      "I-DatePublication",
      "B-Titre",
      "I-Titre",
      "I-Titre",
      "I-Titre",
      "I-Titre",
      "I-Titre",
      "I-Titre",
      "I-Titre",
      "I-Titre",
      "I-Titre",
      "I-Titre",
      "I-Titre",
      "I-Titre",
      "I-Titre",
      "I-Titre",
      "I-Titre",
      "I-Titre",
      "I-Titre",
      "I-Titre",
      "I-Titre",
      "I-Titre",
      "I-Titre",
      "B-Titre",
      "I-Titre",
      "I-Titre",
      "I-Titre",
      "I-Titre",
      "I-Titre",
      "I-Titre",
      "I-Titre",
      "I-Titre",
      "I-Titre",
      "B-Pages",
      "I-Pages"
    ]
  },
  {
    "words": [
      "Clauzel,",
      "A.",
      "A.",
      "Lombardot,",
      "E.",
      "E.",
      "&",
      "Rich\u00e9,",
      "C.",
      "C.",
      "2015",
      "2015",
      "Manger",
      "local",
      "au",
      "restaurant:",
      "un",
      "nouveau",
      "march\u00e9,",
      "de",
      "nouvelles",
      "attentes?",
      "attentes?",
      "Gestion",
      "2000",
      "2000"
    ],
    "labels": [
      "B-Auteur",
      "I-Auteur",
      "I-Auteur",
      "B-Auteur",
      "I-Auteur",
      "I-Auteur",
      "O",
      "B-Auteur",
      "I-Auteur",
      "I-Auteur",
      "B-DatePublication",
      "I-DatePublication",
      "B-Titre",
      "I-Titre",
      "I-Titre",
      "I-Titre",
      "I-Titre",
      "I-Titre",
      "I-Titre",
      "I-Titre",
      "I-Titre",
      "I-Titre",
      "I-Titre",
      "B-TitreRevue",
      "I-TitreRevue",
      "I-TitreRevue"
    ]
  },
  {
    "words": [
      "Gaultier-Gaillard",
      "(Cros)",
      "(Cros)",
      "S.",
      "&",
      "Breka,",
      "J.N.",
      "J.N.",
      "2013",
      "2013",
      "Quelles",
      "sont",
      "les",
      "r\u00e9ticences",
      "\u00e0",
      "la",
      "mise",
      "en",
      "place",
      "d\u2019une",
      "cha\u00eene",
      "logistique",
      "verte",
      "dans",
      "les",
      "entreprises",
      "entreprises",
      "Revue",
      "Fran\u00e7aise",
      "de",
      "Gestion",
      "Industrielle",
      "Industrielle",
      "32",
      "32",
      "2",
      "2"
    ],
    "labels": [
      "B-Auteur",
      "I-Auteur",
      "I-Auteur",
      "B-Auteur",
      "I-Auteur",
      "I-Auteur",
      "I-Auteur",
      "I-Auteur",
      "B-DatePublication",
      "I-DatePublication",
      "B-Titre",
      "I-Titre",
      "I-Titre",
      "I-Titre",
      "I-Titre",
      "I-Titre",
      "I-Titre",
      "I-Titre",
      "I-Titre",
      "I-Titre",
      "I-Titre",
      "I-Titre",
      "I-Titre",
      "I-Titre",
      "I-Titre",
      "I-Titre",
      "I-Titre",
      "B-TitreRevue",
      "I-TitreRevue",
      "I-TitreRevue",
      "I-TitreRevue",
      "I-TitreRevue",
      "I-TitreRevue",
      "B-Volume",
      "I-Volume",
      "B-Numero",
      "I-Numero"
    ]
  },
  {
    "words": [
      "Karakas,",
      "S.",
      "S.",
      "&",
      "Kilic,",
      "S.",
      "S.",
      "2016",
      "2016",
      "Le",
      "succ\u00e8s",
      "de",
      "carri\u00e8re",
      "chez",
      "les",
      "ing\u00e9nieurs",
      "ing\u00e9nieurs",
      "Revue",
      "internationale",
      "de",
      "psychosociologie",
      "et",
      "de",
      "gestion",
      "des",
      "comportements",
      "organisationnels",
      "organisationnels"
    ],
    "labels": [
      "B-Auteur",
      "I-Auteur",
      "I-Auteur",
      "O",
      "B-Auteur",
      "I-Auteur",
      "I-Auteur",
      "B-DatePublication",
      "I-DatePublication",
      "B-Titre",
      "I-Titre",
      "I-Titre",
      "I-Titre",
      "I-Titre",
      "I-Titre",
      "I-Titre",
      "I-Titre",
      "B-TitreRevue",
      "I-TitreRevue",
      "I-TitreRevue",
      "I-TitreRevue",
      "I-TitreRevue",
      "I-TitreRevue",
      "I-TitreRevue",
      "I-TitreRevue",
      "I-TitreRevue",
      "I-TitreRevue",
      "I-TitreRevue"
    ]
  },
  {
    "words": [
      "de",
      "La",
      "Robertie",
      "Robertie",
      "C.",
      "&",
      "Latour,",
      "X.",
      "X.",
      "2016",
      "2016",
      "(Ed.),",
      "N\u00b0",
      "sp\u00e9cial:",
      "L'entreprise",
      "et",
      "la",
      "S\u00e9curit\u00e9",
      "S\u00e9curit\u00e9",
      "Les",
      "Cahiers",
      "de",
      "la",
      "S\u00e9curit\u00e9",
      "et",
      "de",
      "la",
      "Justice",
      "Justice",
      "(AERES",
      "Droit),",
      "34",
      "34",
      "janvier",
      "2016",
      "2016"
    ],
    "labels": [
      "B-EditeurScientifique",
      "I-EditeurScientifique",
      "I-EditeurScientifique",
      "I-EditeurScientifique",
      "B-EditeurScientifique",
      "I-EditeurScientifique",
      "I-EditeurScientifique",
      "I-EditeurScientifique",
      "I-EditeurScientifique",
      "B-DatePublication",
      "I-DatePublication",
      "O",
      "B-Titre",
      "I-Titre",
      "I-Titre",
      "I-Titre",
      "I-Titre",
      "I-Titre",
      "I-Titre",
      "B-TitreRevue",
      "I-TitreRevue",
      "I-TitreRevue",
      "I-TitreRevue",
      "I-TitreRevue",
      "I-TitreRevue",
      "I-TitreRevue",
      "I-TitreRevue",
      "I-TitreRevue",
      "I-TitreRevue",
      "O",
      "O",
      "B-Volume",
      "I-Volume",
      "B-DatePublication",
      "I-DatePublication",
      "I-DatePublication"
    ]
  },
  {
    "words": [
      "de",
      "La",
      "Robertie,",
      "C.",
      "C.",
      "Gitelman,",
      "L.",
      "L.",
      "&",
      "Danilov,",
      "S.",
      "S.",
      "2012",
      "2012",
      "La",
      "s\u00e9curit\u00e9",
      "\u00e9nerg\u00e9tique",
      "en",
      "Russie",
      ":",
      "le",
      "cas",
      "de",
      "l\u2019industrie",
      "\u00e9lectrique",
      "\u00e9lectrique",
      "Les",
      "Cahiers",
      "de",
      "la",
      "S\u00e9curit\u00e9",
      "et",
      "de",
      "la",
      "justice",
      "justice",
      "(AERES",
      "droit),",
      "21",
      "21",
      "octobre",
      "2012",
      "2012",
      "pp.",
      "104-109",
      "104-109"
    ],
    "labels": [
      "B-Auteur",
      "I-Auteur",
      "I-Auteur",
      "I-Auteur",
      "I-Auteur",
      "B-Auteur",
      "I-Auteur",
      "I-Auteur",
      "O",
      "B-Auteur",
      "I-Auteur",
      "I-Auteur",
      "B-DatePublication",
      "I-DatePublication",
      "B-Titre",
      "I-Titre",
      "I-Titre",
      "I-Titre",
      "I-Titre",
      "I-Titre",
      "I-Titre",
      "I-Titre",
      "I-Titre",
      "I-Titre",
      "I-Titre",
      "I-Titre",
      "B-Titre",
      "I-Titre",
      "I-Titre",
      "I-Titre",
      "I-Titre",
      "I-Titre",
      "I-Titre",
      "I-Titre",
      "I-Titre",
      "I-Titre",
      "O",
      "O",
      "B-TitreRevue",
      "I-TitreRevue",
      "B-DatePublication",
      "I-DatePublication",
      "I-DatePublication",
      "O",
      "B-Pages",
      "I-Pages"
    ]
  },
  {
    "words": [
      "Pluchart,",
      "J.",
      "J.",
      "J.",
      "2013",
      "2013",
      "La",
      "gouvernance",
      "des",
      "entreprises",
      "socialement",
      "responsables",
      "responsables",
      "Recherches",
      "en",
      "Sciences",
      "de",
      "Gestion",
      "Gestion",
      "1",
      "1"
    ],
    "labels": [
      "B-Auteur",
      "I-Auteur",
      "I-Auteur",
      "I-Auteur",
      "B-DatePublication",
      "I-DatePublication",
      "B-Titre",
      "I-Titre",
      "I-Titre",
      "I-Titre",
      "I-Titre",
      "I-Titre",
      "I-Titre",
      "B-TitreRevue",
      "I-TitreRevue",
      "I-TitreRevue",
      "I-TitreRevue",
      "I-TitreRevue",
      "I-TitreRevue",
      "B-Volume",
      "I-Volume"
    ]
  },
  {
    "words": [
      "Clauzel,",
      "A.",
      "A.",
      "&",
      "Rich\u00e9,",
      "C.",
      "C.",
      "2013",
      "2013",
      "Relation-client",
      "et",
      "gestion",
      "du",
      "temps",
      "de",
      "consommation",
      ":",
      "quel",
      "r\u00f4le",
      "du",
      "sourire",
      "du",
      "personnel",
      "en",
      "contact",
      "en",
      "restauration",
      "?",
      "?",
      "Customer",
      "relationship",
      "and",
      "meal",
      "duration:",
      "what",
      "impacts",
      "of",
      "front-line",
      "employees'",
      "smiling?",
      "smiling?",
      "Revue",
      "Fran\u00e7aise",
      "du",
      "Marketing",
      "Marketing"
    ],
    "labels": [
      "B-Auteur",
      "I-Auteur",
      "I-Auteur",
      "O",
      "B-Auteur",
      "I-Auteur",
      "I-Auteur",
      "B-DatePublication",
      "I-DatePublication",
      "B-Titre",
      "I-Titre",
      "I-Titre",
      "I-Titre",
      "I-Titre",
      "I-Titre",
      "I-Titre",
      "I-Titre",
      "I-Titre",
      "I-Titre",
      "I-Titre",
      "I-Titre",
      "I-Titre",
      "I-Titre",
      "I-Titre",
      "I-Titre",
      "I-Titre",
      "I-Titre",
      "I-Titre",
      "I-Titre",
      "B-Titre",
      "I-Titre",
      "I-Titre",
      "I-Titre",
      "I-Titre",
      "I-Titre",
      "I-Titre",
      "I-Titre",
      "I-Titre",
      "I-Titre",
      "I-Titre",
      "I-Titre",
      "B-TitreRevue",
      "I-TitreRevue",
      "I-TitreRevue",
      "I-TitreRevue",
      "I-TitreRevue"
    ]
  },
  {
    "words": [
      "Clauzel,",
      "A.",
      "A.",
      "Rich\u00e9,",
      "C.",
      "C.",
      "&",
      "Vidal,",
      "M.",
      "M.",
      "2016",
      "2016",
      "Origine",
      "continentale",
      "du",
      "visiteur",
      "et",
      "exp\u00e9rience",
      "au",
      "mus\u00e9e.",
      "Une",
      "approche",
      "interculturelle",
      "des",
      "avis",
      "en",
      "ligne",
      "ligne",
      "Visitor's",
      "continental",
      "origin",
      "and",
      "museum",
      "experience:",
      "an",
      "intercultural",
      "approach",
      "of",
      "online",
      "reviews",
      "reviews",
      "Revue",
      "Fran\u00e7aise",
      "du",
      "Marketing",
      "Marketing"
    ],
    "labels": [
      "B-Auteur",
      "I-Auteur",
      "I-Auteur",
      "B-Auteur",
      "I-Auteur",
      "I-Auteur",
      "O",
      "B-Auteur",
      "I-Auteur",
      "I-Auteur",
      "B-DatePublication",
      "I-DatePublication",
      "B-Titre",
      "I-Titre",
      "I-Titre",
      "I-Titre",
      "I-Titre",
      "I-Titre",
      "I-Titre",
      "I-Titre",
      "I-Titre",
      "I-Titre",
      "I-Titre",
      "I-Titre",
      "I-Titre",
      "I-Titre",
      "I-Titre",
      "I-Titre",
      "B-Titre",
      "I-Titre",
      "I-Titre",
      "I-Titre",
      "I-Titre",
      "I-Titre",
      "I-Titre",
      "I-Titre",
      "I-Titre",
      "I-Titre",
      "I-Titre",
      "I-Titre",
      "I-Titre",
      "B-TitreRevue",
      "I-TitreRevue",
      "I-TitreRevue",
      "I-TitreRevue",
      "I-TitreRevue"
    ]
  },
  {
    "words": [
      "Jacquinot,",
      "P.",
      "P.",
      "&",
      "Pellissier-Tanon,",
      "A.",
      "A.",
      "2012",
      "2012",
      "Une",
      "dimension",
      "oubli\u00e9e",
      "du",
      "management:",
      "la",
      "fragilit\u00e9.",
      "Une",
      "\u00e9tude",
      "exploratoire",
      "exploratoire",
      "La",
      "revue",
      "des",
      "sciences",
      "de",
      "gestion",
      "gestion",
      "1",
      "1"
    ],
    "labels": [
      "B-Auteur",
      "I-Auteur",
      "I-Auteur",
      "O",
      "B-Auteur",
      "I-Auteur",
      "I-Auteur",
      "B-DatePublication",
      "I-DatePublication",
      "B-Titre",
      "I-Titre",
      "I-Titre",
      "I-Titre",
      "I-Titre",
      "I-Titre",
      "I-Titre",
      "I-Titre",
      "I-Titre",
      "I-Titre",
      "I-Titre",
      "B-TitreRevue",
      "I-TitreRevue",
      "I-TitreRevue",
      "I-TitreRevue",
      "I-TitreRevue",
      "I-TitreRevue",
      "I-TitreRevue",
      "B-Volume",
      "I-Volume"
    ]
  },
  {
    "words": [
      "Gillet",
      "R.",
      "R.",
      "&",
      "Ledent,",
      "P.",
      "P.",
      "2013",
      "2013",
      "March\u00e9s",
      "des",
      "capitaux,",
      "co\u00fbt",
      "du",
      "capital,",
      "investissement",
      "et",
      "emploi",
      "emploi",
      "Revue",
      "Bancaire",
      "et",
      "Financi\u00e8re",
      "Financi\u00e8re",
      "3",
      "3",
      "195-203",
      "195-203"
    ],
    "labels": [
      "B-Auteur",
      "I-Auteur",
      "I-Auteur",
      "O",
      "B-Auteur",
      "I-Auteur",
      "I-Auteur",
      "B-DatePublication",
      "I-DatePublication",
      "B-Titre",
      "I-Titre",
      "I-Titre",
      "I-Titre",
      "I-Titre",
      "I-Titre",
      "I-Titre",
      "I-Titre",
      "I-Titre",
      "I-Titre",
      "B-TitreRevue",
      "I-TitreRevue",
      "I-TitreRevue",
      "I-TitreRevue",
      "I-TitreRevue",
      "B-Volume",
      "I-Volume",
      "B-Pages",
      "I-Pages"
    ]
  },
  {
    "words": [
      "Vanheems,",
      "R.",
      "R.",
      "2013",
      "2013",
      "La",
      "distribution",
      "\u00e0",
      "l'heure",
      "du",
      "multi-canal:",
      "une",
      "red\u00e9finition",
      "du",
      "r\u00f4le",
      "du",
      "vendeur",
      "vendeur",
      "D\u00e9cisions",
      "marketing",
      "marketing"
    ],
    "labels": [
      "B-Auteur",
      "I-Auteur",
      "I-Auteur",
      "B-DatePublication",
      "I-DatePublication",
      "B-Titre",
      "I-Titre",
      "I-Titre",
      "I-Titre",
      "I-Titre",
      "I-Titre",
      "I-Titre",
      "I-Titre",
      "I-Titre",
      "I-Titre",
      "I-Titre",
      "I-Titre",
      "I-Titre",
      "B-TitreRevue",
      "I-TitreRevue",
      "I-TitreRevue"
    ]
  },
  {
    "words": [
      "Aissi,",
      "L.",
      "B.",
      "F.",
      "F.",
      "M.",
      "Naudin",
      "Naudin",
      "&",
      "V.",
      "Neveu",
      "Neveu",
      "2015",
      "2015",
      "Les",
      "strat\u00e9gies",
      "d\u2019ajustement",
      "de",
      "t\u00e9l\u00e9op\u00e9rateurs",
      "de",
      "centres",
      "d\u2019appels",
      "face",
      "au",
      "stress",
      "g\u00e9n\u00e9r\u00e9",
      "par",
      "le",
      "monitoring",
      "\u00e9lectronique",
      "des",
      "performances",
      "performances",
      "La",
      "Revue",
      "des",
      "Sciences",
      "de",
      "Gestion",
      "Gestion",
      "5",
      "5"
    ],
    "labels": [
      "B-Auteur",
      "I-Auteur",
      "I-Auteur",
      "I-Auteur",
      "I-Auteur",
      "B-Auteur",
      "I-Auteur",
      "I-Auteur",
      "O",
      "B-Auteur",
      "I-Auteur",
      "I-Auteur",
      "B-DatePublication",
      "I-DatePublication",
      "B-Titre",
      "I-Titre",
      "I-Titre",
      "I-Titre",
      "I-Titre",
      "I-Titre",
      "I-Titre",
      "I-Titre",
      "I-Titre",
      "I-Titre",
      "I-Titre",
      "I-Titre",
      "I-Titre",
      "I-Titre",
      "I-Titre",
      "I-Titre",
      "I-Titre",
      "I-Titre",
      "I-Titre",
      "B-TitreRevue",
      "I-TitreRevue",
      "I-TitreRevue",
      "I-TitreRevue",
      "I-TitreRevue",
      "I-TitreRevue",
      "I-TitreRevue",
      "B-Volume",
      "I-Volume"
    ]
  },
  {
    "words": [
      "Breka,",
      "J.",
      "N.",
      "N.",
      "&",
      "Gaultier-Gaillard",
      "(Cros),",
      "S.",
      "S.",
      "2013",
      "2013",
      "La",
      "supply",
      "chain",
      "verte",
      "dans",
      "les",
      "entreprises",
      "agroalimentaires",
      "fran\u00e7aises:",
      "freins",
      "et",
      "motivations",
      "motivations",
      "Gestion",
      "2000",
      "2000"
    ],
    "labels": [
      "B-Auteur",
      "I-Auteur",
      "I-Auteur",
      "I-Auteur",
      "O",
      "B-Auteur",
      "I-Auteur",
      "I-Auteur",
      "I-Auteur",
      "B-DatePublication",
      "I-DatePublication",
      "B-Titre",
      "I-Titre",
      "I-Titre",
      "I-Titre",
      "I-Titre",
      "I-Titre",
      "I-Titre",
      "I-Titre",
      "I-Titre",
      "I-Titre",
      "I-Titre",
      "I-Titre",
      "I-Titre",
      "B-TitreRevue",
      "I-TitreRevue",
      "I-TitreRevue"
    ]
  },
  {
    "words": [
      "Clauzel,",
      "A.",
      "A.",
      "&",
      "Rich\u00e9,",
      "C.",
      "C.",
      "2013",
      "2013",
      "\u00c9valuation",
      "en",
      "ligne",
      "et",
      "r\u00e9cits",
      "d'exp\u00e9riences",
      "au",
      "restaurant:",
      "quels",
      "effets",
      "de",
      "l'\u00e2ge",
      "de",
      "l'e-\u00e9valuateur?",
      "l'e-\u00e9valuateur?",
      "Gestion",
      "2000",
      "2000"
    ],
    "labels": [
      "B-Auteur",
      "I-Auteur",
      "I-Auteur",
      "O",
      "B-Auteur",
      "I-Auteur",
      "I-Auteur",
      "B-DatePublication",
      "I-DatePublication",
      "B-Titre",
      "I-Titre",
      "I-Titre",
      "I-Titre",
      "I-Titre",
      "I-Titre",
      "I-Titre",
      "I-Titre",
      "I-Titre",
      "I-Titre",
      "I-Titre",
      "I-Titre",
      "I-Titre",
      "I-Titre",
      "I-Titre",
      "B-TitreRevue",
      "I-TitreRevue",
      "I-TitreRevue"
    ]
  },
  {
    "words": [
      "Combe,",
      "E.",
      "E.",
      "&",
      "Monnier-Schlumberger,",
      "C.",
      "C.",
      "2016",
      "2016",
      "Lutte",
      "contre",
      "les",
      "cartels",
      "et",
      "comportement",
      "des",
      "managers",
      "managers",
      "Concurrences",
      "Review",
      "Review",
      "4",
      "4"
    ],
    "labels": [
      "B-Auteur",
      "I-Auteur",
      "I-Auteur",
      "O",
      "B-Auteur",
      "I-Auteur",
      "I-Auteur",
      "B-DatePublication",
      "I-DatePublication",
      "B-Titre",
      "I-Titre",
      "I-Titre",
      "I-Titre",
      "I-Titre",
      "I-Titre",
      "I-Titre",
      "I-Titre",
      "I-Titre",
      "B-TitreRevue",
      "I-TitreRevue",
      "I-TitreRevue",
      "B-Volume",
      "I-Volume"
    ]
  },
  {
    "words": [
      "Condomines,",
      "B.",
      "B.",
      "&",
      "Hennequin,",
      "E.",
      "E.",
      "2013",
      "2013",
      "Etudier",
      "des",
      "sujets",
      "sensibles:",
      "les",
      "apports",
      "d'une",
      "approche",
      "mixte",
      "mixte",
      "RIMHE:",
      "Revue",
      "Interdisciplinaire",
      "Management,",
      "Homme",
      "&",
      "Entreprise",
      "Entreprise",
      "1",
      "1"
    ],
    "labels": [
      "B-Auteur",
      "I-Auteur",
      "I-Auteur",
      "O",
      "B-Auteur",
      "I-Auteur",
      "I-Auteur",
      "B-DatePublication",
      "I-DatePublication",
      "B-Titre",
      "I-Titre",
      "I-Titre",
      "I-Titre",
      "I-Titre",
      "I-Titre",
      "I-Titre",
      "I-Titre",
      "I-Titre",
      "I-Titre",
      "B-TitreRevue",
      "I-TitreRevue",
      "I-TitreRevue",
      "I-TitreRevue",
      "I-TitreRevue",
      "I-TitreRevue",
      "I-TitreRevue",
      "I-TitreRevue",
      "B-Volume",
      "I-Volume"
    ]
  },
  {
    "words": [
      "Damay,",
      "C.",
      "C.",
      "&",
      "Guichard,",
      "N.",
      "N.",
      "2013",
      "2013",
      "display",
      "in",
      "toys",
      "catalogue",
      "and",
      "children's",
      "cognitive",
      "process",
      "due",
      "to",
      "this",
      "Pr\u00e9sentation",
      "des",
      "prix",
      "dans",
      "les",
      "catalogues",
      "de",
      "jouets",
      "et",
      "traitement",
      "cognitif",
      "des",
      "prix",
      "induits",
      "chez",
      "les",
      "enfants.",
      "enfants.",
      "Revue",
      "Fran\u00e7aise",
      "du",
      "Marketing",
      "Marketing",
      "243",
      "243"
    ],
    "labels": [
      "B-Auteur",
      "I-Auteur",
      "I-Auteur",
      "O",
      "B-Auteur",
      "I-Auteur",
      "I-Auteur",
      "B-DatePublication",
      "I-DatePublication",
      "O",
      "O",
      "O",
      "O",
      "O",
      "O",
      "O",
      "O",
      "O",
      "O",
      "O",
      "B-Titre",
      "I-Titre",
      "I-Titre",
      "I-Titre",
      "I-Titre",
      "I-Titre",
      "I-Titre",
      "I-Titre",
      "I-Titre",
      "I-Titre",
      "I-Titre",
      "I-Titre",
      "I-Titre",
      "I-Titre",
      "I-Titre",
      "I-Titre",
      "I-Titre",
      "I-Titre",
      "B-TitreRevue",
      "I-TitreRevue",
      "I-TitreRevue",
      "I-TitreRevue",
      "I-TitreRevue",
      "B-Volume",
      "I-Volume"
    ]
  },
  {
    "words": [
      "Goffin,",
      "M.",
      "M.",
      "2014",
      "2014",
      "Lien",
      "entre",
      "d\u00e9cision",
      "d'investissement",
      "et",
      "d\u00e9cision",
      "de",
      "remboursement",
      "obligataire",
      "anticip\u00e9",
      "avec",
      "refinancement:",
      "incidence",
      "sur",
      "le",
      "timing",
      "optimal",
      "de",
      "remboursement",
      "anticip\u00e9",
      "anticip\u00e9",
      "La",
      "Revue",
      "des",
      "Sciences",
      "de",
      "Gestion",
      "Gestion",
      "3",
      "3",
      "171-182",
      "171-182"
    ],
    "labels": [
      "B-Auteur",
      "I-Auteur",
      "I-Auteur",
      "B-DatePublication",
      "I-DatePublication",
      "B-Titre",
      "I-Titre",
      "I-Titre",
      "I-Titre",
      "I-Titre",
      "I-Titre",
      "I-Titre",
      "I-Titre",
      "I-Titre",
      "I-Titre",
      "I-Titre",
      "I-Titre",
      "I-Titre",
      "I-Titre",
      "I-Titre",
      "I-Titre",
      "I-Titre",
      "I-Titre",
      "I-Titre",
      "I-Titre",
      "I-Titre",
      "B-TitreRevue",
      "I-TitreRevue",
      "I-TitreRevue",
      "I-TitreRevue",
      "I-TitreRevue",
      "I-TitreRevue",
      "I-TitreRevue",
      "B-Volume",
      "I-Volume",
      "B-Pages",
      "I-Pages"
    ]
  },
  {
    "words": [
      "Goffin,",
      "M.",
      "M.",
      "2017",
      "2017",
      "Les",
      "changements",
      "fondamentaux",
      "sur",
      "le",
      "march\u00e9",
      "des",
      "obligations",
      "callables",
      "\u00e9mises",
      "par",
      "les",
      "firmes",
      "am\u00e9ricaines",
      "au",
      "cours",
      "des",
      "40",
      "ann\u00e9es",
      "1974-2013",
      "1974-2013",
      "La",
      "Revue",
      "des",
      "Sciences",
      "de",
      "Gestion",
      "Gestion",
      "A",
      "paraitre",
      "paraitre"
    ],
    "labels": [
      "B-Auteur",
      "I-Auteur",
      "I-Auteur",
      "B-DatePublication",
      "I-DatePublication",
      "B-Titre",
      "I-Titre",
      "I-Titre",
      "I-Titre",
      "I-Titre",
      "I-Titre",
      "I-Titre",
      "I-Titre",
      "I-Titre",
      "I-Titre",
      "I-Titre",
      "I-Titre",
      "I-Titre",
      "I-Titre",
      "I-Titre",
      "I-Titre",
      "I-Titre",
      "I-Titre",
      "I-Titre",
      "I-Titre",
      "I-Titre",
      "B-TitreRevue",
      "I-TitreRevue",
      "I-TitreRevue",
      "I-TitreRevue",
      "I-TitreRevue",
      "I-TitreRevue",
      "I-TitreRevue",
      "B-AParaitre",
      "I-AParaitre",
      "I-AParaitre"
    ]
  },
  {
    "words": [
      "Jacquinot,",
      "P.",
      "P.",
      "&",
      "Pellissier-Tanon,",
      "A.",
      "A.",
      "2015",
      "2015",
      "L\u2019autonomie",
      "de",
      "d\u00e9cision",
      "dans",
      "les",
      "entreprises",
      "lib\u00e9r\u00e9es",
      "de",
      "l\u2019emprise",
      "organisationnelle",
      "organisationnelle",
      "Revue",
      "internationale",
      "de",
      "psychosociologie",
      "et",
      "de",
      "gestion",
      "des",
      "comportements",
      "organisationnels",
      "organisationnels"
    ],
    "labels": [
      "B-Auteur",
      "I-Auteur",
      "I-Auteur",
      "O",
      "B-Auteur",
      "I-Auteur",
      "I-Auteur",
      "B-DatePublication",
      "I-DatePublication",
      "B-Titre",
      "I-Titre",
      "I-Titre",
      "I-Titre",
      "I-Titre",
      "I-Titre",
      "I-Titre",
      "I-Titre",
      "I-Titre",
      "I-Titre",
      "I-Titre",
      "B-TitreRevue",
      "I-TitreRevue",
      "I-TitreRevue",
      "I-TitreRevue",
      "I-TitreRevue",
      "I-TitreRevue",
      "I-TitreRevue",
      "I-TitreRevue",
      "I-TitreRevue",
      "I-TitreRevue",
      "I-TitreRevue"
    ]
  },
  {
    "words": [
      "Sattin,",
      "J.",
      "F.",
      "F.",
      "2012",
      "2012",
      "Proc\u00e9dures",
      "d\u2019audit",
      "et",
      "gestion",
      "des",
      "licences",
      "de",
      "brevet:",
      "une",
      "analyse",
      "transactionnelle",
      "transactionnelle",
      "Revue",
      "d'\u00e9conomie",
      "industrielle",
      "industrielle",
      "139",
      "139"
    ],
    "labels": [
      "B-Auteur",
      "I-Auteur",
      "I-Auteur",
      "I-Auteur",
      "B-DatePublication",
      "I-DatePublication",
      "B-Titre",
      "I-Titre",
      "I-Titre",
      "I-Titre",
      "I-Titre",
      "I-Titre",
      "I-Titre",
      "I-Titre",
      "I-Titre",
      "I-Titre",
      "I-Titre",
      "I-Titre",
      "B-TitreRevue",
      "I-TitreRevue",
      "I-TitreRevue",
      "I-TitreRevue",
      "B-Volume",
      "I-Volume"
    ]
  },
  {
    "words": [
      "Baruel",
      "Bencherqui,",
      "D.",
      "D.",
      "&",
      "Kefi,",
      "M.K.",
      "M.K.",
      "2013",
      "2013",
      "Le",
      "processus",
      "de",
      "validation",
      "des",
      "acquis",
      "de",
      "l\u2019exp\u00e9rience",
      ":",
      "une",
      "analyse",
      "empirique",
      "par",
      "la",
      "th\u00e9orie",
      "du",
      "comportement",
      "planifi\u00e9",
      "planifi\u00e9",
      "Revue",
      "Interdisciplinaire,",
      "Management,",
      "Homme",
      "&",
      "Entreprise",
      "Entreprise",
      "7",
      "7",
      "111-125",
      "111-125"
    ],
    "labels": [
      "B-Auteur",
      "I-Auteur",
      "I-Auteur",
      "I-Auteur",
      "O",
      "B-Auteur",
      "I-Auteur",
      "I-Auteur",
      "B-DatePublication",
      "I-DatePublication",
      "B-Titre",
      "I-Titre",
      "I-Titre",
      "I-Titre",
      "I-Titre",
      "I-Titre",
      "I-Titre",
      "I-Titre",
      "I-Titre",
      "I-Titre",
      "I-Titre",
      "I-Titre",
      "I-Titre",
      "I-Titre",
      "I-Titre",
      "I-Titre",
      "I-Titre",
      "I-Titre",
      "I-Titre",
      "B-TitreRevue",
      "I-TitreRevue",
      "I-TitreRevue",
      "I-TitreRevue",
      "I-TitreRevue",
      "I-TitreRevue",
      "I-TitreRevue",
      "B-Volume",
      "I-Volume",
      "B-Pages",
      "I-Pages"
    ]
  },
  {
    "words": [
      "de",
      "Fabregues,",
      "M.",
      "M.",
      "&",
      "Pluchart,",
      "J.",
      "J.",
      "J.",
      "2014",
      "2014",
      "La",
      "r\u00e9gression",
      "psychique",
      "individuelle",
      "est-elle",
      "inh\u00e9rente",
      "au",
      "processus",
      "organisationnel",
      "de",
      "normalisation?",
      "normalisation?",
      "Revue",
      "internationale",
      "de",
      "psychosociologie",
      "et",
      "de",
      "gestion",
      "des",
      "comportements",
      "organisationnels",
      "organisationnels"
    ],
    "labels": [
      "B-Auteur",
      "I-Auteur",
      "I-Auteur",
      "I-Auteur",
      "O",
      "B-Auteur",
      "I-Auteur",
      "I-Auteur",
      "I-Auteur",
      "B-DatePublication",
      "I-DatePublication",
      "B-Titre",
      "I-Titre",
      "I-Titre",
      "I-Titre",
      "I-Titre",
      "I-Titre",
      "I-Titre",
      "I-Titre",
      "I-Titre",
      "I-Titre",
      "I-Titre",
      "I-Titre",
      "B-TitreRevue",
      "I-TitreRevue",
      "I-TitreRevue",
      "I-TitreRevue",
      "I-TitreRevue",
      "I-TitreRevue",
      "I-TitreRevue",
      "I-TitreRevue",
      "I-TitreRevue",
      "I-TitreRevue",
      "I-TitreRevue"
    ]
  },
  {
    "words": [
      "Hennequin,",
      "E.",
      "E.",
      "&",
      "Wielhorski,",
      "N.",
      "N.",
      "2012",
      "2012",
      "Quand",
      "l'intime",
      "s'",
      "immisce",
      "dans",
      "l'entreprise",
      "l'entreprise",
      "RIMHE:",
      "Revue",
      "Interdisciplinaire",
      "Management,",
      "Homme",
      "&",
      "Entreprise",
      "Entreprise",
      "4",
      "4",
      "42-56",
      "42-56"
    ],
    "labels": [
      "B-Auteur",
      "I-Auteur",
      "I-Auteur",
      "O",
      "B-Auteur",
      "I-Auteur",
      "I-Auteur",
      "B-DatePublication",
      "I-DatePublication",
      "B-Titre",
      "I-Titre",
      "I-Titre",
      "I-Titre",
      "I-Titre",
      "I-Titre",
      "I-Titre",
      "B-TitreRevue",
      "I-TitreRevue",
      "I-TitreRevue",
      "I-TitreRevue",
      "I-TitreRevue",
      "I-TitreRevue",
      "I-TitreRevue",
      "I-TitreRevue",
      "B-Volume",
      "I-Volume",
      "B-Pages",
      "I-Pages"
    ]
  },
  {
    "words": [
      "Kossa\u00ef,",
      "M.",
      "M.",
      "&",
      "Piget,",
      "P.",
      "P.",
      "2012",
      "2012",
      "Utilisation",
      "des",
      "technologies",
      "de",
      "l\u2019information",
      "et",
      "des",
      "communication",
      "(TIC)",
      "et",
      "performance",
      "\u00e9conomique",
      "des",
      "PME",
      "tunisiennes\u00a0:",
      "une",
      "\u00e9tude",
      "\u00e9conom\u00e9trique",
      "\u00e9conom\u00e9trique",
      "Brussels",
      "Economic",
      "Review",
      "Review",
      "55",
      "55",
      "2",
      "2"
    ],
    "labels": [
      "B-Auteur",
      "I-Auteur",
      "I-Auteur",
      "O",
      "B-Auteur",
      "I-Auteur",
      "I-Auteur",
      "B-DatePublication",
      "I-DatePublication",
      "B-Titre",
      "I-Titre",
      "I-Titre",
      "I-Titre",
      "I-Titre",
      "I-Titre",
      "I-Titre",
      "I-Titre",
      "I-Titre",
      "I-Titre",
      "I-Titre",
      "I-Titre",
      "I-Titre",
      "I-Titre",
      "I-Titre",
      "I-Titre",
      "I-Titre",
      "I-Titre",
      "I-Titre",
      "B-TitreRevue",
      "I-TitreRevue",
      "I-TitreRevue",
      "I-TitreRevue",
      "B-Volume",
      "I-Volume",
      "B-Numero",
      "I-Numero"
    ]
  },
  {
    "words": [
      "Monnier-Schlumberger,",
      "C.",
      "C.",
      "&",
      "Hutin,",
      "A.",
      "A.",
      "2016",
      "2016",
      "Les",
      "cartels",
      "en",
      "France\u00a0:",
      "Analyse",
      "\u00e9conomique",
      "de",
      "leurs",
      "caract\u00e9ristiques",
      "et",
      "de",
      "leurs",
      "sanctions",
      "sanctions",
      "Revue",
      "Concurrences",
      "Concurrences",
      "2",
      "2",
      "45-61",
      "45-61"
    ],
    "labels": [
      "B-Auteur",
      "I-Auteur",
      "I-Auteur",
      "O",
      "B-Auteur",
      "I-Auteur",
      "I-Auteur",
      "B-DatePublication",
      "I-DatePublication",
      "B-Titre",
      "I-Titre",
      "I-Titre",
      "I-Titre",
      "I-Titre",
      "I-Titre",
      "I-Titre",
      "I-Titre",
      "I-Titre",
      "I-Titre",
      "I-Titre",
      "I-Titre",
      "I-Titre",
      "I-Titre",
      "B-TitreRevue",
      "I-TitreRevue",
      "I-TitreRevue",
      "B-Volume",
      "I-Volume",
      "B-Pages",
      "I-Pages"
    ]
  },
  {
    "words": [
      "Penin,",
      "P.",
      "P.",
      "2016)",
      "2016)",
      "Les",
      "collaborateurs",
      "issus",
      "de",
      "l\u2019immigration",
      "dans",
      "les",
      "entreprises",
      "fran\u00e7aises:",
      "le",
      "cas",
      "de",
      "10",
      "comit\u00e9s",
      "ex\u00e9cutifs",
      "du",
      "CAC",
      "40",
      "40",
      "Question",
      "(s)",
      "de",
      "management",
      "management",
      "3",
      "3"
    ],
    "labels": [
      "B-Auteur",
      "I-Auteur",
      "I-Auteur",
      "B-DatePublication",
      "I-DatePublication",
      "B-Titre",
      "I-Titre",
      "I-Titre",
      "I-Titre",
      "I-Titre",
      "I-Titre",
      "I-Titre",
      "I-Titre",
      "I-Titre",
      "I-Titre",
      "I-Titre",
      "I-Titre",
      "I-Titre",
      "I-Titre",
      "I-Titre",
      "I-Titre",
      "I-Titre",
      "I-Titre",
      "I-Titre",
      "B-TitreRevue",
      "I-TitreRevue",
      "I-TitreRevue",
      "I-TitreRevue",
      "I-TitreRevue",
      "B-Volume",
      "I-Volume"
    ]
  },
  {
    "words": [
      "Rich\u00e9,",
      "C.",
      "C.",
      "Vidal,",
      "M.",
      "M.",
      "&",
      "Clauzel,",
      "A.",
      "A.",
      "2014",
      "2014",
      "Transmettre",
      "son",
      "exp\u00e9rience",
      "au",
      "mus\u00e9e",
      "par",
      "les",
      "avis",
      "en",
      "ligne:",
      "tout",
      "d\u00e9pend",
      "du",
      "sexe!",
      "sexe!",
      "Question",
      "(s)",
      "de",
      "management",
      "management",
      "1",
      "1"
    ],
    "labels": [
      "B-Auteur",
      "I-Auteur",
      "I-Auteur",
      "B-Auteur",
      "I-Auteur",
      "I-Auteur",
      "O",
      "B-Auteur",
      "I-Auteur",
      "I-Auteur",
      "B-DatePublication",
      "I-DatePublication",
      "B-Titre",
      "I-Titre",
      "I-Titre",
      "I-Titre",
      "I-Titre",
      "I-Titre",
      "I-Titre",
      "I-Titre",
      "I-Titre",
      "I-Titre",
      "I-Titre",
      "I-Titre",
      "I-Titre",
      "I-Titre",
      "I-Titre",
      "B-TitreRevue",
      "I-TitreRevue",
      "I-TitreRevue",
      "I-TitreRevue",
      "I-TitreRevue",
      "B-Volume",
      "I-Volume"
    ]
  },
  {
    "words": [
      "Vanheems,",
      "R.",
      "R.",
      "2012",
      "2012",
      "Imbrication",
      "entre",
      "espace",
      "virtuel",
      "et",
      "espace",
      "physique:",
      "quand",
      "les",
      "vendeurs",
      "s'en",
      "m\u00ealent...",
      "m\u00ealent...",
      "Revue",
      "Fran\u00e7aise",
      "du",
      "Marketing",
      "Marketing",
      "237/238",
      "237/238"
    ],
    "labels": [
      "B-Auteur",
      "I-Auteur",
      "I-Auteur",
      "B-DatePublication",
      "I-DatePublication",
      "B-Titre",
      "I-Titre",
      "I-Titre",
      "I-Titre",
      "I-Titre",
      "I-Titre",
      "I-Titre",
      "I-Titre",
      "I-Titre",
      "I-Titre",
      "I-Titre",
      "I-Titre",
      "I-Titre",
      "B-TitreRevue",
      "I-TitreRevue",
      "I-TitreRevue",
      "I-TitreRevue",
      "I-TitreRevue",
      "B-Volume",
      "I-Volume"
    ]
  },
  {
    "words": [
      "Muratore",
      "I.",
      "I.",
      "et",
      "Guichard",
      "N.",
      "N.",
      "2012",
      "2012",
      "Approche",
      "s\u00e9miotique",
      "de",
      "la",
      "repr\u00e9sentation",
      "form\u00e9e",
      "par",
      "les",
      "enfants",
      "des",
      "packagings",
      "de",
      "c\u00e9r\u00e9ales",
      "bonnes",
      "pour",
      "la",
      "sant\u00e9",
      "sant\u00e9",
      "Perspectives",
      "Culturelles",
      "de",
      "la",
      "Consommation",
      "Consommation",
      "2",
      "2",
      "1",
      "1",
      "39-62",
      "39-62"
    ],
    "labels": [
      "B-Auteur",
      "I-Auteur",
      "I-Auteur",
      "O",
      "B-Auteur",
      "I-Auteur",
      "I-Auteur",
      "B-DatePublication",
      "I-DatePublication",
      "B-Titre",
      "I-Titre",
      "I-Titre",
      "I-Titre",
      "I-Titre",
      "I-Titre",
      "I-Titre",
      "I-Titre",
      "I-Titre",
      "I-Titre",
      "I-Titre",
      "I-Titre",
      "I-Titre",
      "I-Titre",
      "I-Titre",
      "I-Titre",
      "I-Titre",
      "I-Titre",
      "B-TitreRevue",
      "I-TitreRevue",
      "I-TitreRevue",
      "I-TitreRevue",
      "I-TitreRevue",
      "I-TitreRevue",
      "B-Volume",
      "I-Volume",
      "B-Numero",
      "I-Numero",
      "B-Pages",
      "I-Pages"
    ]
  },
  {
    "words": [
      "Aissi,",
      "L.",
      "B.",
      "F.",
      "F.",
      "&",
      "Neveu,",
      "V.",
      "V.",
      "2015",
      "2015",
      "Mieux",
      "comprendre",
      "les",
      "caract\u00e9ristiques",
      "d\u2019un",
      "monitoring",
      "\u00e9lectronique",
      "des",
      "performances",
      "acceptable",
      "par",
      "les",
      "salari\u00e9s,",
      "\u00e0",
      "la",
      "lumi\u00e8re",
      "des",
      "th\u00e9ories",
      "de",
      "la",
      "justice",
      "organisationnelle",
      "organisationnelle",
      "Revue",
      "de",
      "gestion",
      "des",
      "ressources",
      "humaines",
      "humaines",
      "3",
      "3"
    ],
    "labels": [
      "B-Auteur",
      "I-Auteur",
      "I-Auteur",
      "I-Auteur",
      "I-Auteur",
      "O",
      "B-Auteur",
      "I-Auteur",
      "I-Auteur",
      "B-DatePublication",
      "I-DatePublication",
      "B-Titre",
      "I-Titre",
      "I-Titre",
      "I-Titre",
      "I-Titre",
      "I-Titre",
      "I-Titre",
      "I-Titre",
      "I-Titre",
      "I-Titre",
      "I-Titre",
      "I-Titre",
      "I-Titre",
      "I-Titre",
      "I-Titre",
      "I-Titre",
      "I-Titre",
      "I-Titre",
      "I-Titre",
      "I-Titre",
      "I-Titre",
      "I-Titre",
      "I-Titre",
      "B-TitreRevue",
      "I-TitreRevue",
      "I-TitreRevue",
      "I-TitreRevue",
      "I-TitreRevue",
      "I-TitreRevue",
      "I-TitreRevue",
      "B-Volume",
      "I-Volume"
    ]
  },
  {
    "words": [
      "Cloet,",
      "H.",
      "H.",
      "&",
      "Hennequin,",
      "E.",
      "E.",
      "2014",
      "2014",
      "Chronique.",
      "La",
      "praticabilit\u00e9",
      "des",
      "recherches",
      "actuelles",
      "en",
      "GRH:",
      "les",
      "th\u00e9matiques,",
      "m\u00e9thodologies",
      "et",
      "collaborations",
      "du",
      "24e",
      "congr\u00e8s",
      "de",
      "l'AGRH",
      "et",
      "leur",
      "mise",
      "en",
      "perspective",
      "perspective",
      "Revue",
      "de",
      "gestion",
      "des",
      "ressources",
      "humaines",
      "humaines",
      "3",
      "3"
    ],
    "labels": [
      "B-Auteur",
      "I-Auteur",
      "I-Auteur",
      "O",
      "B-Auteur",
      "I-Auteur",
      "I-Auteur",
      "B-DatePublication",
      "I-DatePublication",
      "B-Titre",
      "I-Titre",
      "I-Titre",
      "I-Titre",
      "I-Titre",
      "I-Titre",
      "I-Titre",
      "I-Titre",
      "I-Titre",
      "I-Titre",
      "I-Titre",
      "I-Titre",
      "I-Titre",
      "I-Titre",
      "I-Titre",
      "I-Titre",
      "I-Titre",
      "I-Titre",
      "I-Titre",
      "I-Titre",
      "I-Titre",
      "I-Titre",
      "I-Titre",
      "I-Titre",
      "B-TitreRevue",
      "I-TitreRevue",
      "I-TitreRevue",
      "I-TitreRevue",
      "I-TitreRevue",
      "I-TitreRevue",
      "I-TitreRevue",
      "B-Volume",
      "I-Volume"
    ]
  },
  {
    "words": [
      "Combe,",
      "E.",
      "E.",
      "&",
      "Monnier-Schlumberger,",
      "C.",
      "C.",
      "2016",
      "2016",
      "Cartels",
      "et",
      "comportements",
      "des",
      "managers:",
      "analyse",
      "et",
      "implications",
      "pour",
      "les",
      "politiques",
      "publiques",
      "publiques",
      "Revue",
      "\u00e9conomique",
      "\u00e9conomique",
      "67",
      "67",
      "HS1",
      "HS1"
    ],
    "labels": [
      "B-Auteur",
      "I-Auteur",
      "I-Auteur",
      "O",
      "B-Auteur",
      "I-Auteur",
      "I-Auteur",
      "B-DatePublication",
      "I-DatePublication",
      "B-Titre",
      "I-Titre",
      "I-Titre",
      "I-Titre",
      "I-Titre",
      "I-Titre",
      "I-Titre",
      "I-Titre",
      "I-Titre",
      "I-Titre",
      "I-Titre",
      "I-Titre",
      "I-Titre",
      "B-TitreRevue",
      "I-TitreRevue",
      "I-TitreRevue",
      "B-Volume",
      "I-Volume",
      "B-Numero",
      "I-Numero"
    ]
  },
  {
    "words": [
      "Vanheems,",
      "R.",
      "R.",
      "2012",
      "2012",
      "Cross-canal:",
      "comment",
      "le",
      "site",
      "Internet",
      "d\u2019une",
      "enseigne",
      "modifie",
      "le",
      "comportement",
      "de",
      "ses",
      "clients",
      "en",
      "magasin",
      "magasin",
      "Revue",
      "Fran\u00e7aise",
      "de",
      "Gestion",
      "Gestion"
    ],
    "labels": [
      "B-Auteur",
      "I-Auteur",
      "I-Auteur",
      "B-DatePublication",
      "I-DatePublication",
      "B-Titre",
      "I-Titre",
      "I-Titre",
      "I-Titre",
      "I-Titre",
      "I-Titre",
      "I-Titre",
      "I-Titre",
      "I-Titre",
      "I-Titre",
      "I-Titre",
      "I-Titre",
      "I-Titre",
      "I-Titre",
      "I-Titre",
      "I-Titre",
      "B-TitreRevue",
      "I-TitreRevue",
      "I-TitreRevue",
      "I-TitreRevue",
      "I-TitreRevue"
    ]
  },
  {
    "words": [
      "Badot,",
      "O.",
      "O.",
      "&",
      "Lemoine,",
      "J.",
      "F.",
      "F.",
      "2015",
      "2015",
      "\u00c9largissement",
      "des",
      "principes",
      "de",
      "l\u2019attractivit\u00e9",
      "commerciale",
      "\u00e0",
      "ceux",
      "de",
      "l\u2019attractivit\u00e9",
      "touristique:",
      "le",
      "cas",
      "de",
      "La",
      "Vall\u00e9e",
      "Village",
      "\u00e0",
      "Marne-la-Vall\u00e9e",
      "Marne-la-Vall\u00e9e",
      "Management",
      "&",
      "Avenir",
      "Avenir",
      "3",
      "3"
    ],
    "labels": [
      "B-Auteur",
      "I-Auteur",
      "I-Auteur",
      "O",
      "B-Auteur",
      "I-Auteur",
      "I-Auteur",
      "I-Auteur",
      "B-DatePublication",
      "I-DatePublication",
      "B-Titre",
      "I-Titre",
      "I-Titre",
      "I-Titre",
      "I-Titre",
      "I-Titre",
      "I-Titre",
      "I-Titre",
      "I-Titre",
      "I-Titre",
      "I-Titre",
      "I-Titre",
      "I-Titre",
      "I-Titre",
      "I-Titre",
      "I-Titre",
      "I-Titre",
      "I-Titre",
      "I-Titre",
      "I-Titre",
      "B-TitreRevue",
      "I-TitreRevue",
      "I-TitreRevue",
      "I-TitreRevue",
      "B-Volume",
      "I-Volume"
    ]
  },
  {
    "words": [
      "Chanson,",
      "G.",
      "G.",
      "&",
      "Edouard,",
      "S.",
      "S.",
      "2013",
      "2013",
      "L'\u00e9volution",
      "d'un",
      "r\u00e9seau",
      "social",
      "dans",
      "une",
      "r\u00e9organisation:\u00abfluctuat",
      "nec",
      "mergitur\u00bb",
      "mergitur\u00bb",
      "@",
      "GRH",
      "GRH",
      "2",
      "2"
    ],
    "labels": [
      "B-Auteur",
      "I-Auteur",
      "I-Auteur",
      "O",
      "B-Auteur",
      "I-Auteur",
      "I-Auteur",
      "B-DatePublication",
      "I-DatePublication",
      "B-Titre",
      "I-Titre",
      "I-Titre",
      "I-Titre",
      "I-Titre",
      "I-Titre",
      "I-Titre",
      "I-Titre",
      "I-Titre",
      "I-Titre",
      "B-TitreRevue",
      "I-TitreRevue",
      "I-TitreRevue",
      "B-Volume",
      "I-Volume"
    ]
  },
  {
    "words": [
      "Damay,",
      "C.",
      "C.",
      "Guichard,",
      "N.",
      "N.",
      "&",
      "Clauzel,",
      "A.",
      "A.",
      "2014",
      "2014",
      "Effets",
      "de",
      "forme",
      "et",
      "de",
      "terminaison",
      "des",
      "prix:",
      "une",
      "comparaison",
      "enfants\u2013adultes",
      "enfants\u2013adultes",
      "Management",
      "&",
      "Avenir",
      "Avenir",
      "6",
      "6"
    ],
    "labels": [
      "B-Auteur",
      "I-Auteur",
      "I-Auteur",
      "B-Auteur",
      "I-Auteur",
      "I-Auteur",
      "O",
      "B-Auteur",
      "I-Auteur",
      "I-Auteur",
      "B-DatePublication",
      "I-DatePublication",
      "B-Titre",
      "I-Titre",
      "I-Titre",
      "I-Titre",
      "I-Titre",
      "I-Titre",
      "I-Titre",
      "I-Titre",
      "I-Titre",
      "I-Titre",
      "I-Titre",
      "I-Titre",
      "B-TitreRevue",
      "I-TitreRevue",
      "I-TitreRevue",
      "I-TitreRevue",
      "B-Volume",
      "I-Volume"
    ]
  },
  {
    "words": [
      "Drucker-Godard,",
      "C.",
      "C.",
      "Fouque,",
      "T.",
      "T.",
      "Gollety,",
      "M.",
      "M.",
      "&",
      "Le",
      "Flanchec,",
      "A.",
      "A.",
      "2017",
      "2017",
      "Enseignant-chercheur",
      "au",
      "f\u00e9minin:",
      "la",
      "place",
      "des",
      "femmes",
      "dans",
      "les",
      "universit\u00e9s",
      "universit\u00e9s",
      "Recherches",
      "en",
      "Sciences",
      "de",
      "Gestion",
      "Gestion",
      "1",
      "1"
    ],
    "labels": [
      "B-Auteur",
      "I-Auteur",
      "I-Auteur",
      "B-Auteur",
      "I-Auteur",
      "I-Auteur",
      "B-Auteur",
      "I-Auteur",
      "I-Auteur",
      "O",
      "B-Auteur",
      "I-Auteur",
      "I-Auteur",
      "I-Auteur",
      "B-DatePublication",
      "I-DatePublication",
      "B-Titre",
      "I-Titre",
      "I-Titre",
      "I-Titre",
      "I-Titre",
      "I-Titre",
      "I-Titre",
      "I-Titre",
      "I-Titre",
      "I-Titre",
      "I-Titre",
      "B-TitreRevue",
      "I-TitreRevue",
      "I-TitreRevue",
      "I-TitreRevue",
      "I-TitreRevue",
      "I-TitreRevue",
      "B-Volume",
      "I-Volume"
    ]
  },
  {
    "words": [
      "Le",
      "Flanchec,",
      "A.",
      "A.",
      "Mullenbach-Servayre,",
      "A.",
      "A.",
      "&",
      "Rojot,",
      "J.",
      "J.",
      "2015",
      "2015",
      "Favoriser",
      "la",
      "satisfaction",
      "au",
      "travail:",
      "les",
      "apports",
      "de",
      "l\u2019enqu\u00eate",
      "REPONSE",
      "2011",
      "2011",
      "Management",
      "&",
      "Avenir",
      "Avenir",
      "7",
      "7"
    ],
    "labels": [
      "B-Auteur",
      "I-Auteur",
      "I-Auteur",
      "I-Auteur",
      "B-Auteur",
      "I-Auteur",
      "I-Auteur",
      "O",
      "B-Auteur",
      "I-Auteur",
      "I-Auteur",
      "B-DatePublication",
      "I-DatePublication",
      "B-Titre",
      "I-Titre",
      "I-Titre",
      "I-Titre",
      "I-Titre",
      "I-Titre",
      "I-Titre",
      "I-Titre",
      "I-Titre",
      "I-Titre",
      "I-Titre",
      "I-Titre",
      "B-TitreRevue",
      "I-TitreRevue",
      "I-TitreRevue",
      "I-TitreRevue",
      "B-Volume",
      "I-Volume"
    ]
  },
  {
    "words": [
      "PROST",
      "Antoine",
      "Antoine",
      "\u00ab",
      "Pr\u00e9face",
      "Pr\u00e9face",
      "\u00bb,",
      "dans",
      "GUTIERREZ",
      "Laurent",
      "Laurent",
      "et",
      "LEGRIS",
      "Patricia",
      "Patricia",
      "Le",
      "Coll\u00e8ge",
      "unique.",
      "\u00c9clairages",
      "socio-historiques",
      "sur",
      "la",
      "loi",
      "du",
      "11",
      "juillet",
      "1975",
      "1975",
      "Rennes",
      "Rennes",
      "Presses",
      "universitaires",
      "de",
      "Rennes",
      "Rennes",
      "2016",
      "2016",
      "256",
      "p.,",
      "p.",
      "9-",
      "9-"
    ],
    "labels": [
      "B-Auteur",
      "I-Auteur",
      "I-Auteur",
      "O",
      "B-Titre",
      "I-Titre",
      "O",
      "O",
      "B-EditeurScientifique",
      "I-EditeurScientifique",
      "I-EditeurScientifique",
      "O",
      "B-EditeurScientifique",
      "I-EditeurScientifique",
      "I-EditeurScientifique",
      "B-TitreOuvrageCollectif",
      "I-TitreOuvrageCollectif",
      "I-TitreOuvrageCollectif",
      "I-TitreOuvrageCollectif",
      "I-TitreOuvrageCollectif",
      "I-TitreOuvrageCollectif",
      "I-TitreOuvrageCollectif",
      "I-TitreOuvrageCollectif",
      "I-TitreOuvrageCollectif",
      "I-TitreOuvrageCollectif",
      "I-TitreOuvrageCollectif",
      "I-TitreOuvrageCollectif",
      "I-TitreOuvrageCollectif",
      "B-LieuPublication",
      "I-LieuPublication",
      "B-EditeurCommercial",
      "I-EditeurCommercial",
      "I-EditeurCommercial",
      "I-EditeurCommercial",
      "I-EditeurCommercial",
      "B-DatePublication",
      "I-DatePublication",
      "O",
      "O",
      "O",
      "B-Pages",
      "I-Pages"
    ]
  },
  {
    "words": [
      "VOLDMAN",
      "Dani\u00e8le",
      "Dani\u00e8le",
      "\u00ab",
      "Les",
      "mod\u00e8les",
      "urbains",
      "d\u2019Henri",
      "Sellier",
      "et",
      "leur",
      "mise",
      "en",
      "\u0153uvre",
      "\u00e0",
      "l\u2019Office",
      "d\u00e9partemental",
      "d\u2019HBM",
      "de",
      "la",
      "Seine",
      "Seine",
      "\u00bb,",
      "Histoire",
      "urbaine",
      "urbaine",
      "n\u00b0",
      "37",
      "37",
      "ao\u00fbt",
      "2013",
      "2013",
      "p.",
      "95-106",
      "95-106"
    ],
    "labels": [
      "B-Auteur",
      "I-Auteur",
      "I-Auteur",
      "O",
      "B-Titre",
      "I-Titre",
      "I-Titre",
      "I-Titre",
      "I-Titre",
      "I-Titre",
      "I-Titre",
      "I-Titre",
      "I-Titre",
      "I-Titre",
      "I-Titre",
      "I-Titre",
      "I-Titre",
      "I-Titre",
      "I-Titre",
      "I-Titre",
      "I-Titre",
      "I-Titre",
      "O",
      "B-TitreRevue",
      "I-TitreRevue",
      "I-TitreRevue",
      "O",
      "B-Volume",
      "I-Volume",
      "B-DatePublication",
      "I-DatePublication",
      "I-DatePublication",
      "O",
      "B-Pages",
      "I-Pages"
    ]
  },
  {
    "words": [
      "PIGENET",
      "Michel",
      "Michel",
      "\u00ab",
      "Histoire",
      "Histoire",
      "\u00bb,",
      "dans",
      "BEVORT",
      "Antoine",
      "Antoine",
      "JOBERT",
      "Annette",
      "Annette",
      "LALLEMENT",
      "Michel",
      "Michel",
      "MIAS",
      "Arnaud",
      "Arnaud",
      "Dictionnaire",
      "du",
      "travail",
      "travail",
      "Paris",
      "Paris",
      "PUF",
      "PUF",
      "2012",
      "2012",
      "p.",
      "366-",
      "366-"
    ],
    "labels": [
      "B-Auteur",
      "I-Auteur",
      "I-Auteur",
      "O",
      "B-Titre",
      "I-Titre",
      "O",
      "O",
      "B-EditeurScientifique",
      "I-EditeurScientifique",
      "I-EditeurScientifique",
      "B-EditeurScientifique",
      "I-EditeurScientifique",
      "I-EditeurScientifique",
      "B-EditeurScientifique",
      "I-EditeurScientifique",
      "I-EditeurScientifique",
      "B-EditeurScientifique",
      "I-EditeurScientifique",
      "I-EditeurScientifique",
      "B-TitreOuvrageCollectif",
      "I-TitreOuvrageCollectif",
      "I-TitreOuvrageCollectif",
      "I-TitreOuvrageCollectif",
      "B-LieuPublication",
      "I-LieuPublication",
      "B-EditeurCommercial",
      "I-EditeurCommercial",
      "B-DatePublication",
      "I-DatePublication",
      "O",
      "B-Pages",
      "I-Pages"
    ]
  }
]